Workbook

Sheet Start Here
A1: Start Here
A2: A simple paycheck budget that does the math for you.
A4: HOW IT WORKS
A5: 1. Setup | C5: Enter your paychecks' dates, categories, accounts, funds and debts. Edit once.
A6: 2. Paycheck Budget | C6: Plan each category across Paycheck 1 and Paycheck 2.
A7: 3. Transactions | C7: Log income, expenses and transfers. Everything else fills in.
A9: COLOR KEY
A10: Blue text | C10: You type it.
A11: Dark text | C11: Calculated — do not edit.
A13: THE TABS
A14: Setup | C14: Your paychecks, categories, accounts, funds, debts.
A15: Dashboard | C15: Your month at a glance. Updates itself.
A16: Paycheck Budget | C16: Plan vs actual, split by paycheck.
A17: Transactions | C17: Log income, expenses and transfers.
A18: Bill Calendar | C18: Weekly to yearly bills shown as a fair monthly cost.
A19: Savings | C19: Sinking funds with progress to each goal.
A20: Debt | C20: List debts smallest first and watch them shrink.
A22: Works in Google Sheets AND Excel. Formulas are protected — only the blue cells are yours to edit.
A23: This is an organisation tool, not financial advice.

Sheet Setup
A1: Setup
A2: Edit once — your paychecks, categories, accounts, funds and debts.
B4: Currency | C4: $ | E4: Month start | F4: 46204 | H4: Paycheck 1 date | I4: 46206 | J4: Paycheck 2 date | K4: 46220
B6: INCOME SOURCES | D6: EXPENSE CATEGORIES | F6: ACCOUNTS | H6: SAVINGS FUNDS | J6: DEBTS | M6: freq | N6: x / month | P6: categories + funds — helper for the Transactions dropdown, you can hide column P
B7: Paycheck 1 | D7: Rent or Mortgage | F7: Checking | H7: Emergency Fund | J7: Credit Card | M7: Weekly | N7: 4.3333 | P7: =IF(D7="","",D7)
B8: Paycheck 2 | D8: Utilities | F8: Savings | H8: Holiday | J8: Car loan | M8: Biweekly | N8: 2.1667 | P8: =IF(D8="","",D8)
B9: Extra Income | D9: Groceries | F9: Cash | H9: New Car | J9: Student loan | M9: Monthly | N9: 1 | P9: =IF(D9="","",D9)
D10: Transport | F10: Credit Card | H10: Vacation | M10: Yearly | N10: 0.0833 | P10: =IF(D10="","",D10)
D11: Dining out | H11: Home Repairs | P11: =IF(D11="","",D11)
D12: Subscriptions | M12: helper for Bill Calendar — you can hide columns M:N | P12: =IF(D12="","",D12)
D13: Health | P13: =IF(D13="","",D13)
D14: Insurance | P14: =IF(D14="","",D14)
D15: Phone and Internet | P15: =IF(D15="","",D15)
D16: Shopping | P16: =IF(D16="","",D16)
D17: Fun and Leisure | P17: =IF(D17="","",D17)
D18: Gifts | P18: =IF(D18="","",D18)
P19: =IF(D19="","",D19)
P20: =IF(D20="","",D20)
P21: =IF(D21="","",D21)
P22: =IF(D22="","",D22)
P23: =IF(D23="","",D23)
P24: =IF(D24="","",D24)
P25: =IF(D25="","",D25)
P26: =IF(D26="","",D26)
P27: =IF(H7="","",H7)
P28: =IF(H8="","",H8)
P29: =IF(H9="","",H9)
P30: =IF(H10="","",H10)
P31: =IF(H11="","",H11)
P32: =IF(H12="","",H12)

Sheet Dashboard
A1: Dashboard
A2: Nothing to fill in here. It updates itself from your tabs.
B4: =CHOOSE(MONTH(Setup!$F$4),"January","February","March","April","May","June","July","August","September","October","November","December")&" "&YEAR(Setup!$F$4)
B6: INCOME | D6: EXPENSES | F6: SAVED | H6: LEFT
B7: =SUMIFS(Transactions!$F$5:$F$504,Transactions!$B$5:$B$504,"Income",Transactions!$A$5:$A$504,">="&Setup!$F$4,Transactions!$A$5:$A$504,"<"&EDATE(Setup!$F$4,1)) | D7: =SUMIFS(Transactions!$F$5:$F$504,Transactions!$B$5:$B$504,"Expense",Transactions!$A$5:$A$504,">="&Setup!$F$4,Transactions!$A$5:$A$504,"<"&EDATE(Setup!$F$4,1)) | F7: =SUMIFS(Transactions!$F$5:$F$504,Transactions!$B$5:$B$504,"Transfer",Transactions!$A$5:$A$504,">="&Setup!$F$4,Transactions!$A$5:$A$504,"<"&EDATE(Setup!$F$4,1)) | H7: =B7-D7-F7
B10: PAYCHECK SPLIT | E10: THIS MONTH
B11: Paycheck 1 | C11: =SUMIFS(Transactions!$F$5:$F$504,Transactions!$B$5:$B$504,"Income",Transactions!$E$5:$E$504,"1",Transactions!$A$5:$A$504,">="&Setup!$F$4,Transactions!$A$5:$A$504,"<"&EDATE(Setup!$F$4,1)) | E11: Budget planned | F11: ='Paycheck Budget'!D32
B12: Paycheck 2 | C12: =SUMIFS(Transactions!$F$5:$F$504,Transactions!$B$5:$B$504,"Income",Transactions!$E$5:$E$504,"2",Transactions!$A$5:$A$504,">="&Setup!$F$4,Transactions!$A$5:$A$504,"<"&EDATE(Setup!$F$4,1)) | E12: Bills / month | F12: ='Bill Calendar'!D17
E13: Saved to funds | F13: =SUMIFS(Transactions!$F$5:$F$504,Transactions!$B$5:$B$504,"Transfer",Transactions!$A$5:$A$504,">="&Setup!$F$4,Transactions!$A$5:$A$504,"<"&EDATE(Setup!$F$4,1))
E14: Debt remaining | F14: =Debt!D11
E15: Funds target | F15: =SUM(Savings!B5:B10)
B18: SPENDING BY CATEGORY (this month)
B19: Category | C19: Spent
B20: =IF(Setup!D7="","",Setup!D7) | C20: =IF(B20="","",SUMIFS(Transactions!$F$5:$F$504,Transactions!$B$5:$B$504,"Expense",Transactions!$C$5:$C$504,B20,Transactions!$A$5:$A$504,">="&Setup!$F$4,Transactions!$A$5:$A$504,"<"&EDATE(Setup!$F$4,1)))
B21: =IF(Setup!D8="","",Setup!D8) | C21: =IF(B21="","",SUMIFS(Transactions!$F$5:$F$504,Transactions!$B$5:$B$504,"Expense",Transactions!$C$5:$C$504,B21,Transactions!$A$5:$A$504,">="&Setup!$F$4,Transactions!$A$5:$A$504,"<"&EDATE(Setup!$F$4,1)))
B22: =IF(Setup!D9="","",Setup!D9) | C22: =IF(B22="","",SUMIFS(Transactions!$F$5:$F$504,Transactions!$B$5:$B$504,"Expense",Transactions!$C$5:$C$504,B22,Transactions!$A$5:$A$504,">="&Setup!$F$4,Transactions!$A$5:$A$504,"<"&EDATE(Setup!$F$4,1)))
B23: =IF(Setup!D10="","",Setup!D10) | C23: =IF(B23="","",SUMIFS(Transactions!$F$5:$F$504,Transactions!$B$5:$B$504,"Expense",Transactions!$C$5:$C$504,B23,Transactions!$A$5:$A$504,">="&Setup!$F$4,Transactions!$A$5:$A$504,"<"&EDATE(Setup!$F$4,1)))
B24: =IF(Setup!D11="","",Setup!D11) | C24: =IF(B24="","",SUMIFS(Transactions!$F$5:$F$504,Transactions!$B$5:$B$504,"Expense",Transactions!$C$5:$C$504,B24,Transactions!$A$5:$A$504,">="&Setup!$F$4,Transactions!$A$5:$A$504,"<"&EDATE(Setup!$F$4,1)))
B25: =IF(Setup!D12="","",Setup!D12) | C25: =IF(B25="","",SUMIFS(Transactions!$F$5:$F$504,Transactions!$B$5:$B$504,"Expense",Transactions!$C$5:$C$504,B25,Transactions!$A$5:$A$504,">="&Setup!$F$4,Transactions!$A$5:$A$504,"<"&EDATE(Setup!$F$4,1)))
B26: =IF(Setup!D13="","",Setup!D13) | C26: =IF(B26="","",SUMIFS(Transactions!$F$5:$F$504,Transactions!$B$5:$B$504,"Expense",Transactions!$C$5:$C$504,B26,Transactions!$A$5:$A$504,">="&Setup!$F$4,Transactions!$A$5:$A$504,"<"&EDATE(Setup!$F$4,1)))
B27: =IF(Setup!D14="","",Setup!D14) | C27: =IF(B27="","",SUMIFS(Transactions!$F$5:$F$504,Transactions!$B$5:$B$504,"Expense",Transactions!$C$5:$C$504,B27,Transactions!$A$5:$A$504,">="&Setup!$F$4,Transactions!$A$5:$A$504,"<"&EDATE(Setup!$F$4,1)))
B28: =IF(Setup!D15="","",Setup!D15) | C28: =IF(B28="","",SUMIFS(Transactions!$F$5:$F$504,Transactions!$B$5:$B$504,"Expense",Transactions!$C$5:$C$504,B28,Transactions!$A$5:$A$504,">="&Setup!$F$4,Transactions!$A$5:$A$504,"<"&EDATE(Setup!$F$4,1)))
B29: =IF(Setup!D16="","",Setup!D16) | C29: =IF(B29="","",SUMIFS(Transactions!$F$5:$F$504,Transactions!$B$5:$B$504,"Expense",Transactions!$C$5:$C$504,B29,Transactions!$A$5:$A$504,">="&Setup!$F$4,Transactions!$A$5:$A$504,"<"&EDATE(Setup!$F$4,1)))
B30: =IF(Setup!D17="","",Setup!D17) | C30: =IF(B30="","",SUMIFS(Transactions!$F$5:$F$504,Transactions!$B$5:$B$504,"Expense",Transactions!$C$5:$C$504,B30,Transactions!$A$5:$A$504,">="&Setup!$F$4,Transactions!$A$5:$A$504,"<"&EDATE(Setup!$F$4,1)))
B31: =IF(Setup!D18="","",Setup!D18) | C31: =IF(B31="","",SUMIFS(Transactions!$F$5:$F$504,Transactions!$B$5:$B$504,"Expense",Transactions!$C$5:$C$504,B31,Transactions!$A$5:$A$504,">="&Setup!$F$4,Transactions!$A$5:$A$504,"<"&EDATE(Setup!$F$4,1)))
... B39: =IF(Setup!D26="","",Setup!D26) | C39: =IF(B39="","",SUMIFS(Transactions!$F$5:$F$504,Transactions!$B$5:$B$504,"Expense",Transactions!$C$5:$C$504,B39,Transactions!$A$5:$A$504,">="&Setup!$F$4,Transactions!$A$5:$A$504,"<"&EDATE(Setup!$F$4,1)))

Sheet Paycheck Budget
A1: Paycheck Budget
A2: Split each category across Paycheck 1 and Paycheck 2. Actual pulls from Transactions.
A4: PAYCHECK INCOME THIS MONTH
A5: Paycheck 1 | C5: =SUMIFS(Transactions!$F$5:$F$504,Transactions!$B$5:$B$504,"Income",Transactions!$E$5:$E$504,"1",Transactions!$A$5:$A$504,">="&Setup!$F$4,Transactions!$A$5:$A$504,"<"&EDATE(Setup!$F$4,1))
A6: Paycheck 2 | C6: =SUMIFS(Transactions!$F$5:$F$504,Transactions!$B$5:$B$504,"Income",Transactions!$E$5:$E$504,"2",Transactions!$A$5:$A$504,">="&Setup!$F$4,Transactions!$A$5:$A$504,"<"&EDATE(Setup!$F$4,1))
A7: Extra | C7: =SUMIFS(Transactions!$F$5:$F$504,Transactions!$B$5:$B$504,"Income",Transactions!$E$5:$E$504,"Extra",Transactions!$A$5:$A$504,">="&Setup!$F$4,Transactions!$A$5:$A$504,"<"&EDATE(Setup!$F$4,1))
A8: Total to budget | C8: =SUM(C5:C7)
A9: Left to budget | C9: =C8-D32
A11: Category | B11: Planned P1 | C11: Planned P2 | D11: Total Planned | E11: Actual | F11: Left | G11: % used
A12: =IF(Setup!D7="","",Setup!D7) | B12: 1450 | C12: 0 | D12: =B12+C12 | E12: =IF($A12="","",SUMIFS(Transactions!$F$5:$F$504,Transactions!$B$5:$B$504,"Expense",Transactions!$C$5:$C$504,$A12,Transactions!$A$5:$A$504,">="&Setup!$F$4,Transactions!$A$5:$A$504,"<"&EDATE(Setup!$F$4,1))) | F12: =IF($A12="","",D12-E12) | G12: =IF(OR($A12="",D12=0),"",E12/D12)
A13: =IF(Setup!D8="","",Setup!D8) | B13: 90 | C13: 90 | D13: =B13+C13 | E13: =IF($A13="","",SUMIFS(Transactions!$F$5:$F$504,Transactions!$B$5:$B$504,"Expense",Transactions!$C$5:$C$504,$A13,Transactions!$A$5:$A$504,">="&Setup!$F$4,Transactions!$A$5:$A$504,"<"&EDATE(Setup!$F$4,1))) | F13: =IF($A13="","",D13-E13) | G13: =IF(OR($A13="",D13=0),"",E13/D13)
A14: =IF(Setup!D9="","",Setup!D9) | B14: 260 | C14: 260 | D14: =B14+C14 | E14: =IF($A14="","",SUMIFS(Transactions!$F$5:$F$504,Transactions!$B$5:$B$504,"Expense",Transactions!$C$5:$C$504,$A14,Transactions!$A$5:$A$504,">="&Setup!$F$4,Transactions!$A$5:$A$504,"<"&EDATE(Setup!$F$4,1))) | F14: =IF($A14="","",D14-E14) | G14: =IF(OR($A14="",D14=0),"",E14/D14)
A15: =IF(Setup!D10="","",Setup!D10) | B15: 120 | C15: 120 | D15: =B15+C15 | E15: =IF($A15="","",SUMIFS(Transactions!$F$5:$F$504,Transactions!$B$5:$B$504,"Expense",Transactions!$C$5:$C$504,$A15,Transactions!$A$5:$A$504,">="&Setup!$F$4,Transactions!$A$5:$A$504,"<"&EDATE(Setup!$F$4,1))) | F15: =IF($A15="","",D15-E15) | G15: =IF(OR($A15="",D15=0),"",E15/D15)
A16: =IF(Setup!D11="","",Setup!D11) | B16: 80 | C16: 70 | D16: =B16+C16 | E16: =IF($A16="","",SUMIFS(Transactions!$F$5:$F$504,Transactions!$B$5:$B$504,"Expense",Transactions!$C$5:$C$504,$A16,Transactions!$A$5:$A$504,">="&Setup!$F$4,Transactions!$A$5:$A$504,"<"&EDATE(Setup!$F$4,1))) | F16: =IF($A16="","",D16-E16) | G16: =IF(OR($A16="",D16=0),"",E16/D16)
A17: =IF(Setup!D12="","",Setup!D12) | B17: 45 | C17: 0 | D17: =B17+C17 | E17: =IF($A17="","",SUMIFS(Transactions!$F$5:$F$504,Transactions!$B$5:$B$504,"Expense",Transactions!$C$5:$C$504,$A17,Transactions!$A$5:$A$504,">="&Setup!$F$4,Transactions!$A$5:$A$504,"<"&EDATE(Setup!$F$4,1))) | F17: =IF($A17="","",D17-E17) | G17: =IF(OR($A17="",D17=0),"",E17/D17)
A18: =IF(Setup!D13="","",Setup!D13) | B18: 60 | C18: 40 | D18: =B18+C18 | E18: =IF($A18="","",SUMIFS(Transactions!$F$5:$F$504,Transactions!$B$5:$B$504,"Expense",Transactions!$C$5:$C$504,$A18,Transactions!$A$5:$A$504,">="&Setup!$F$4,Transactions!$A$5:$A$504,"<"&EDATE(Setup!$F$4,1))) | F18: =IF($A18="","",D18-E18) | G18: =IF(OR($A18="",D18=0),"",E18/D18)
A19: =IF(Setup!D14="","",Setup!D14) | B19: 145 | C19: 0 | D19: =B19+C19 | E19: =IF($A19="","",SUMIFS(Transactions!$F$5:$F$504,Transactions!$B$5:$B$504,"Expense",Transactions!$C$5:$C$504,$A19,Transactions!$A$5:$A$504,">="&Setup!$F$4,Transactions!$A$5:$A$504,"<"&EDATE(Setup!$F$4,1))) | F19: =IF($A19="","",D19-E19) | G19: =IF(OR($A19="",D19=0),"",E19/D19)
A20: =IF(Setup!D15="","",Setup!D15) | B20: 0 | C20: 85 | D20: =B20+C20 | E20: =IF($A20="","",SUMIFS(Transactions!$F$5:$F$504,Transactions!$B$5:$B$504,"Expense",Transactions!$C$5:$C$504,$A20,Transactions!$A$5:$A$504,">="&Setup!$F$4,Transactions!$A$5:$A$504,"<"&EDATE(Setup!$F$4,1))) | F20: =IF($A20="","",D20-E20) | G20: =IF(OR($A20="",D20=0),"",E20/D20)
A21: =IF(Setup!D16="","",Setup!D16) | B21: 100 | C21: 80 | D21: =B21+C21 | E21: =IF($A21="","",SUMIFS(Transactions!$F$5:$F$504,Transactions!$B$5:$B$504,"Expense",Transactions!$C$5:$C$504,$A21,Transactions!$A$5:$A$504,">="&Setup!$F$4,Transactions!$A$5:$A$504,"<"&EDATE(Setup!$F$4,1))) | F21: =IF($A21="","",D21-E21) | G21: =IF(OR($A21="",D21=0),"",E21/D21)
A22: =IF(Setup!D17="","",Setup!D17) | B22: 90 | C22: 70 | D22: =B22+C22 | E22: =IF($A22="","",SUMIFS(Transactions!$F$5:$F$504,Transactions!$B$5:$B$504,"Expense",Transactions!$C$5:$C$504,$A22,Transactions!$A$5:$A$504,">="&Setup!$F$4,Transactions!$A$5:$A$504,"<"&EDATE(Setup!$F$4,1))) | F22: =IF($A22="","",D22-E22) | G22: =IF(OR($A22="",D22=0),"",E22/D22)
A23: =IF(Setup!D18="","",Setup!D18) | B23: 40 | C23: 30 | D23: =B23+C23 | E23: =IF($A23="","",SUMIFS(Transactions!$F$5:$F$504,Transactions!$B$5:$B$504,"Expense",Transactions!$C$5:$C$504,$A23,Transactions!$A$5:$A$504,">="&Setup!$F$4,Transactions!$A$5:$A$504,"<"&EDATE(Setup!$F$4,1))) | F23: =IF($A23="","",D23-E23) | G23: =IF(OR($A23="",D23=0),"",E23/D23)
A24: =IF(Setup!D19="","",Setup!D19) | D24: =B24+C24 | E24: =IF($A24="","",SUMIFS(Transactions!$F$5:$F$504,Transactions!$B$5:$B$504,"Expense",Transactions!$C$5:$C$504,$A24,Transactions!$A$5:$A$504,">="&Setup!$F$4,Transactions!$A$5:$A$504,"<"&EDATE(Setup!$F$4,1))) | F24: =IF($A24="","",D24-E24) | G24: =IF(OR($A24="",D24=0),"",E24/D24)
A25: =IF(Setup!D20="","",Setup!D20) | D25: =B25+C25 | E25: =IF($A25="","",SUMIFS(Transactions!$F$5:$F$504,Transactions!$B$5:$B$504,"Expense",Transactions!$C$5:$C$504,$A25,Transactions!$A$5:$A$504,">="&Setup!$F$4,Transactions!$A$5:$A$504,"<"&EDATE(Setup!$F$4,1))) | F25: =IF($A25="","",D25-E25) | G25: =IF(OR($A25="",D25=0),"",E25/D25)
A26: =IF(Setup!D21="","",Setup!D21) | D26: =B26+C26 | E26: =IF($A26="","",SUMIFS(Transactions!$F$5:$F$504,Transactions!$B$5:$B$504,"Expense",Transactions!$C$5:$C$504,$A26,Transactions!$A$5:$A$504,">="&Setup!$F$4,Transactions!$A$5:$A$504,"<"&EDATE(Setup!$F$4,1))) | F26: =IF($A26="","",D26-E26) | G26: =IF(OR($A26="",D26=0),"",E26/D26)
A27: =IF(Setup!D22="","",Setup!D22) | D27: =B27+C27 | E27: =IF($A27="","",SUMIFS(Transactions!$F$5:$F$504,Transactions!$B$5:$B$504,"Expense",Transactions!$C$5:$C$504,$A27,Transactions!$A$5:$A$504,">="&Setup!$F$4,Transactions!$A$5:$A$504,"<"&EDATE(Setup!$F$4,1))) | F27: =IF($A27="","",D27-E27) | G27: =IF(OR($A27="",D27=0),"",E27/D27)
A28: =IF(Setup!D23="","",Setup!D23) | D28: =B28+C28 | E28: =IF($A28="","",SUMIFS(Transactions!$F$5:$F$504,Transactions!$B$5:$B$504,"Expense",Transactions!$C$5:$C$504,$A28,Transactions!$A$5:$A$504,">="&Setup!$F$4,Transactions!$A$5:$A$504,"<"&EDATE(Setup!$F$4,1))) | F28: =IF($A28="","",D28-E28) | G28: =IF(OR($A28="",D28=0),"",E28/D28)
A29: =IF(Setup!D24="","",Setup!D24) | D29: =B29+C29 | E29: =IF($A29="","",SUMIFS(Transactions!$F$5:$F$504,Transactions!$B$5:$B$504,"Expense",Transactions!$C$5:$C$504,$A29,Transactions!$A$5:$A$504,">="&Setup!$F$4,Transactions!$A$5:$A$504,"<"&EDATE(Setup!$F$4,1))) | F29: =IF($A29="","",D29-E29) | G29: =IF(OR($A29="",D29=0),"",E29/D29)
A30: =IF(Setup!D25="","",Setup!D25) | D30: =B30+C30 | E30: =IF($A30="","",SUMIFS(Transactions!$F$5:$F$504,Transactions!$B$5:$B$504,"Expense",Transactions!$C$5:$C$504,$A30,Transactions!$A$5:$A$504,">="&Setup!$F$4,Transactions!$A$5:$A$504,"<"&EDATE(Setup!$F$4,1))) | F30: =IF($A30="","",D30-E30) | G30: =IF(OR($A30="",D30=0),"",E30/D30)
A31: =IF(Setup!D26="","",Setup!D26) | D31: =B31+C31 | E31: =IF($A31="","",SUMIFS(Transactions!$F$5:$F$504,Transactions!$B$5:$B$504,"Expense",Transactions!$C$5:$C$504,$A31,Transactions!$A$5:$A$504,">="&Setup!$F$4,Transactions!$A$5:$A$504,"<"&EDATE(Setup!$F$4,1))) | F31: =IF($A31="","",D31-E31) | G31: =IF(OR($A31="",D31=0),"",E31/D31)
A32: TOTAL | B32: =SUM(B12:B31) | C32: =SUM(C12:C31) | D32: =SUM(D12:D31) | E32: =SUM(E12:E31) | F32: =SUM(F12:F31) | G32: =IF(D32=0,"",E32/D32)

Sheet Transactions
A1: Transactions
A2: Log every income, expense and transfer here. Everything else fills in.
A4: Date | B4: Type | C4: Category | D4: Account | E4: Paycheck | F4: Amount | G4: Note
A5: 46206 | B5: Income | C5: Paycheck 1 | D5: Checking | E5: 1 | F5: 2100 | G5: Salary
A6: 46206 | B6: Expense | C6: Rent or Mortgage | D6: Checking | E6: 1 | F6: 1450 | G6: July rent
A7: 46206 | B7: Transfer | C7: Emergency Fund | D7: Savings | E7: 1 | F7: 250 | G7: Pay yourself first
A8: 46206 | B8: Transfer | C8: Vacation | D8: Savings | E8: 1 | F8: 120 | G8: Greece 2027
A9: 46207 | B9: Expense | C9: Groceries | D9: Checking | E9: 1 | F9: 118.4 | G9: Weekly shop
A10: 46207 | B10: Expense | C10: Dining out | D10: Credit Card | E10: 1 | F10: 28.5 | G10: Brunch
A11: 46208 | B11: Expense | C11: Transport | D11: Checking | E11: 1 | F11: 62 | G11: Fuel
A12: 46209 | B12: Expense | C12: Subscriptions | D12: Credit Card | E12: 1 | F12: 15.99 | G12: Streaming
A13: 46209 | B13: Expense | C13: Phone and Internet | D13: Checking | E13: 1 | F13: 45 | G13: Mobile
A14: 46210 | B14: Expense | C14: Utilities | D14: Checking | E14: 1 | F14: 88.2 | G14: Electricity
A15: 46211 | B15: Expense | C15: Health | D15: Checking | E15: 1 | F15: 34 | G15: Pharmacy
A16: 46212 | B16: Expense | C16: Groceries | D16: Checking | E16: 1 | F16: 104.75 | G16: Weekly shop
... A46: 46233 | B46: Transfer | C46: Home Repairs | D46: Savings | E46: 2 | F46: 60 | G46: Boiler service

Sheet Bill Calendar
A1: Bill Calendar
A2: Set the frequency, see the true monthly cost, never miss a due day.
A4: Bill | B4: Amount | C4: Frequency | D4: Monthly cost | E4: Due day | F4: Paid?
A5: Rent or Mortgage | B5: 1450 | C5: Monthly | D5: =IFERROR(B5*INDEX(Setup!$N$7:$N$10,MATCH(C5,Setup!$M$7:$M$10,0)),"") | E5: 1 | F5: Yes
A6: Electricity | B6: 88.2 | C6: Monthly | D6: =IFERROR(B6*INDEX(Setup!$N$7:$N$10,MATCH(C6,Setup!$M$7:$M$10,0)),"") | E6: 7 | F6: Yes
A7: Water | B7: 26.5 | C7: Monthly | D7: =IFERROR(B7*INDEX(Setup!$N$7:$N$10,MATCH(C7,Setup!$M$7:$M$10,0)),"") | E7: 16 | F7: Yes
A8: Gas | B8: 61.3 | C8: Monthly | D8: =IFERROR(B8*INDEX(Setup!$N$7:$N$10,MATCH(C8,Setup!$M$7:$M$10,0)),"") | E8: 25 | F8: Yes
A9: Mobile plan | B9: 45 | C9: Monthly | D9: =IFERROR(B9*INDEX(Setup!$N$7:$N$10,MATCH(C9,Setup!$M$7:$M$10,0)),"") | E9: 6 | F9: Yes
A10: Internet | B10: 40 | C10: Monthly | D10: =IFERROR(B10*INDEX(Setup!$N$7:$N$10,MATCH(C10,Setup!$M$7:$M$10,0)),"") | E10: 18 | F10: Yes
A11: Car insurance | B11: 145 | C11: Monthly | D11: =IFERROR(B11*INDEX(Setup!$N$7:$N$10,MATCH(C11,Setup!$M$7:$M$10,0)),"") | E11: 11 | F11: Yes
A12: Streaming | B12: 15.99 | C12: Monthly | D12: =IFERROR(B12*INDEX(Setup!$N$7:$N$10,MATCH(C12,Setup!$M$7:$M$10,0)),"") | E12: 6 | F12: Yes
A13: Music | B13: 12.99 | C13: Monthly | D13: =IFERROR(B13*INDEX(Setup!$N$7:$N$10,MATCH(C13,Setup!$M$7:$M$10,0)),"") | E13: 20 | F13: Yes
A14: Gym | B14: 24 | C14: Weekly | D14: =IFERROR(B14*INDEX(Setup!$N$7:$N$10,MATCH(C14,Setup!$M$7:$M$10,0)),"") | E14: 5 | F14: No
A15: Home insurance | B15: 420 | C15: Yearly | D15: =IFERROR(B15*INDEX(Setup!$N$7:$N$10,MATCH(C15,Setup!$M$7:$M$10,0)),"") | E15: 14 | F15: No
A16: Cloud storage | B16: 9.99 | C16: Monthly | D16: =IFERROR(B16*INDEX(Setup!$N$7:$N$10,MATCH(C16,Setup!$M$7:$M$10,0)),"") | E16: 22 | F16: No
A17: TOTAL / MONTH | D17: =SUM(D5:D16)

Sheet Savings
A1: Savings
A2: Set a target per fund. Log a Transfer in Transactions with the fund name as Category.
A4: Fund | B4: Target | C4: Saved | D4: Left | E4: %
A5: =IF(Setup!H7="","",Setup!H7) | B5: 6000 | C5: =IF($A5="","",SUMIFS(Transactions!$F$5:$F$504,Transactions!$B$5:$B$504,"Transfer",Transactions!$C$5:$C$504,$A5)) | D5: =IF($A5="","",B5-C5) | E5: =IF(OR($A5="",B5=0),"",C5/B5)
A6: =IF(Setup!H8="","",Setup!H8) | B6: 1200 | C6: =IF($A6="","",SUMIFS(Transactions!$F$5:$F$504,Transactions!$B$5:$B$504,"Transfer",Transactions!$C$5:$C$504,$A6)) | D6: =IF($A6="","",B6-C6) | E6: =IF(OR($A6="",B6=0),"",C6/B6)
A7: =IF(Setup!H9="","",Setup!H9) | B7: 9000 | C7: =IF($A7="","",SUMIFS(Transactions!$F$5:$F$504,Transactions!$B$5:$B$504,"Transfer",Transactions!$C$5:$C$504,$A7)) | D7: =IF($A7="","",B7-C7) | E7: =IF(OR($A7="",B7=0),"",C7/B7)
A8: =IF(Setup!H10="","",Setup!H10) | B8: 3500 | C8: =IF($A8="","",SUMIFS(Transactions!$F$5:$F$504,Transactions!$B$5:$B$504,"Transfer",Transactions!$C$5:$C$504,$A8)) | D8: =IF($A8="","",B8-C8) | E8: =IF(OR($A8="",B8=0),"",C8/B8)
A9: =IF(Setup!H11="","",Setup!H11) | B9: 1500 | C9: =IF($A9="","",SUMIFS(Transactions!$F$5:$F$504,Transactions!$B$5:$B$504,"Transfer",Transactions!$C$5:$C$504,$A9)) | D9: =IF($A9="","",B9-C9) | E9: =IF(OR($A9="",B9=0),"",C9/B9)
A10: =IF(Setup!H12="","",Setup!H12) | C10: =IF($A10="","",SUMIFS(Transactions!$F$5:$F$504,Transactions!$B$5:$B$504,"Transfer",Transactions!$C$5:$C$504,$A10)) | D10: =IF($A10="","",B10-C10) | E10: =IF(OR($A10="",B10=0),"",C10/B10)

Sheet Debt
A1: Debt
A2: List debts smallest balance first for the snowball. Remaining updates itself.
A4: Debt | B4: Balance | C4: Paid so far | D4: Remaining | E4: % paid | F4: Min payment
A5: =IF(Setup!J7="","",Setup!J7) | B5: 2450 | C5: 1180 | D5: =IF($A5="","",B5-C5) | E5: =IF(OR($A5="",B5=0),"",C5/B5) | F5: 95
A6: =IF(Setup!J8="","",Setup!J8) | B6: 9800 | C6: 3600 | D6: =IF($A6="","",B6-C6) | E6: =IF(OR($A6="",B6=0),"",C6/B6) | F6: 245
A7: =IF(Setup!J9="","",Setup!J9) | B7: 14200 | C7: 5100 | D7: =IF($A7="","",B7-C7) | E7: =IF(OR($A7="",B7=0),"",C7/B7) | F7: 190
A8: =IF(Setup!J10="","",Setup!J10) | D8: =IF($A8="","",B8-C8) | E8: =IF(OR($A8="",B8=0),"",C8/B8)
A9: =IF(Setup!J11="","",Setup!J11) | D9: =IF($A9="","",B9-C9) | E9: =IF(OR($A9="",B9=0),"",C9/B9)
A10: =IF(Setup!J12="","",Setup!J12) | D10: =IF($A10="","",B10-C10) | E10: =IF(OR($A10="",B10=0),"",C10/B10)
A11: TOTAL | B11: =SUM(B5:B10) | C11: =SUM(C5:C10) | D11: =SUM(D5:D10)
