Workbook

Sheet Start Here
A1: Start Here
A2: A debt payoff plan that does the math for you.
A4: HOW IT WORKS
A5: 1. Setup | C5: List each debt: balance, APR and minimum payment. Pick Snowball,
C6: Avalanche or Custom, and add any extra monthly payment.
A7: 2. Dashboard | C7: See your debt-free date, total interest and payoff order — all calculated.
A8: 3. Debt Tracker | C8: Log what you've paid to watch each debt shrink.
A10: THE METHODS
A11: Snowball | C11: Pays the smallest balance first — quick wins for motivation.
A12: Avalanche | C12: Pays the highest interest first — saves the most money.
A13: Custom | C13: You choose the order in the Custom column on Setup.
A15: COLOR KEY
A16: Blue text | C16: You type it.
A17: Dark text | C17: Calculated — do not edit.
A18: If a debt never pays off | C18: Its minimum payment is below the monthly interest.
C19: Raise that minimum or add an extra monthly amount on Setup.
A20: Works in Google Sheets AND Excel. Formulas are protected — only the blue cells are yours. Handles up to 10 debts and 60 months.
A21: This is an organisation tool, not financial advice.

Sheet Setup
A1: Setup
A2: Enter your debts, pick a method, add any extra monthly payment. Edit once.
B4: Currency | C4: $ | E4: Method | F4: Snowball | H4: Extra / month | I4: 400 | K4: Start date | L4: 46235
A6: Debt | B6: Balance | C6: APR % | D6: Min payment | E6: Custom order | F6: score
A7: Store Card | B7: 640 | C7: 27.9 | D7: 30 | E7: 6 | F7: =IF(B7="",9999999,IF($F$4="Snowball",B7,IF($F$4="Avalanche",1-C7/100,IF(E7="",999,E7))))+(ROW()-6)*0.00001 -> 9999999
A8: Medical Bill | B8: 1200 | C8: 0 | D8: 50 | E8: 5 | F8: =IF(B8="",9999999,IF($F$4="Snowball",B8,IF($F$4="Avalanche",1-C8/100,IF(E8="",999,E8))))+(ROW()-6)*0.00001 -> 9999999
A9: Credit Card A | B9: 8900 | C9: 25.9 | D9: 220 | E9: 3 | F9: =IF(B9="",9999999,IF($F$4="Snowball",B9,IF($F$4="Avalanche",1-C9/100,IF(E9="",999,E9))))+(ROW()-6)*0.00001 -> 9999999
A10: Credit Card B | B10: 3100 | C10: 21.9 | D10: 95 | E10: 4 | F10: =IF(B10="",9999999,IF($F$4="Snowball",B10,IF($F$4="Avalanche",1-C10/100,IF(E10="",999,E10))))+(ROW()-6)*0.00001 -> 9999999
A11: Car Loan | B11: 12800 | C11: 7.4 | D11: 345 | E11: 1 | F11: =IF(B11="",9999999,IF($F$4="Snowball",B11,IF($F$4="Avalanche",1-C11/100,IF(E11="",999,E11))))+(ROW()-6)*0.00001 -> 9999999
A12: Student Loan | B12: 9400 | C12: 4.9 | D12: 205 | E12: 2 | F12: =IF(B12="",9999999,IF($F$4="Snowball",B12,IF($F$4="Avalanche",1-C12/100,IF(E12="",999,E12))))+(ROW()-6)*0.00001 -> 9999999
F13: =IF(B13="",9999999,IF($F$4="Snowball",B13,IF($F$4="Avalanche",1-C13/100,IF(E13="",999,E13))))+(ROW()-6)*0.00001 -> 9999999
F14: =IF(B14="",9999999,IF($F$4="Snowball",B14,IF($F$4="Avalanche",1-C14/100,IF(E14="",999,E14))))+(ROW()-6)*0.00001 -> 9999999
F15: =IF(B15="",9999999,IF($F$4="Snowball",B15,IF($F$4="Avalanche",1-C15/100,IF(E15="",999,E15))))+(ROW()-6)*0.00001 -> 9999999
F16: =IF(B16="",9999999,IF($F$4="Snowball",B16,IF($F$4="Avalanche",1-C16/100,IF(E16="",999,E16))))+(ROW()-6)*0.00001 -> 9999999
F18: helper — you can hide column F

Sheet Dashboard
A1: Dashboard
A2: Your debt-free plan. Nothing to fill in here — it updates from Setup.
B4: =CONCATENATE("Method: ",Setup!F4)
B6: DEBT-FREE DATE | D6: MONTHS TO GO | F6: TOTAL DEBT | H6: TOTAL INTEREST
B7: =IF(SUM(Setup!$B$7:$B$16)=0,"—",IF(Engine!$A$18=0,"Over 60 mo",CHOOSE(MONTH(EDATE(Setup!$L$4,Engine!$A$18)),"Jan","Feb","Mar","Apr","May","Jun","Jul","Aug","Sep","Oct","Nov","Dec")&" "&YEAR(EDATE(Setup!$L$4,Engine!$A$18)))) | D7: =IF(SUM(Setup!$B$7:$B$16)=0,"—",IF(Engine!$A$18=0,">60",Engine!$A$18)) | F7: =SUM(Setup!B7:B16) -> 0 | H7: =SUM(Engine!$C$16:$BJ$16) -> 0
B10: Total paid (debt + interest) | E10: =SUM(Setup!B7:B16)+SUM(Engine!$C$16:$BJ$16) -> 0
B11: Paid so far | E11: ='Debt Tracker'!C15 -> 0
B12: Progress | E12: =IF(SUM(Setup!B7:B16)=0,0,'Debt Tracker'!C15/SUM(Setup!B7:B16)) -> 0
B14: PAYOFF ORDER | F14: BALANCE OVER TIME
B15: # | C15: Debt
B16: 1 | C16: =IFERROR(IF(SMALL(Setup!$F$7:$F$16,1)>=9999999,"",INDEX(Setup!$A$7:$A$16,MATCH(SMALL(Setup!$F$7:$F$16,1),Setup!$F$7:$F$16,0))),"")
B17: 2 | C17: =IFERROR(IF(SMALL(Setup!$F$7:$F$16,2)>=9999999,"",INDEX(Setup!$A$7:$A$16,MATCH(SMALL(Setup!$F$7:$F$16,2),Setup!$F$7:$F$16,0))),"")
B18: 3 | C18: =IFERROR(IF(SMALL(Setup!$F$7:$F$16,3)>=9999999,"",INDEX(Setup!$A$7:$A$16,MATCH(SMALL(Setup!$F$7:$F$16,3),Setup!$F$7:$F$16,0))),"")
B19: 4 | C19: =IFERROR(IF(SMALL(Setup!$F$7:$F$16,4)>=9999999,"",INDEX(Setup!$A$7:$A$16,MATCH(SMALL(Setup!$F$7:$F$16,4),Setup!$F$7:$F$16,0))),"")
B20: 5 | C20: =IFERROR(IF(SMALL(Setup!$F$7:$F$16,5)>=9999999,"",INDEX(Setup!$A$7:$A$16,MATCH(SMALL(Setup!$F$7:$F$16,5),Setup!$F$7:$F$16,0))),"")
B21: 6 | C21: =IFERROR(IF(SMALL(Setup!$F$7:$F$16,6)>=9999999,"",INDEX(Setup!$A$7:$A$16,MATCH(SMALL(Setup!$F$7:$F$16,6),Setup!$F$7:$F$16,0))),"")
B22: 7 | C22: =IFERROR(IF(SMALL(Setup!$F$7:$F$16,7)>=9999999,"",INDEX(Setup!$A$7:$A$16,MATCH(SMALL(Setup!$F$7:$F$16,7),Setup!$F$7:$F$16,0))),"")
B23: 8 | C23: =IFERROR(IF(SMALL(Setup!$F$7:$F$16,8)>=9999999,"",INDEX(Setup!$A$7:$A$16,MATCH(SMALL(Setup!$F$7:$F$16,8),Setup!$F$7:$F$16,0))),"")
B24: 9 | C24: =IFERROR(IF(SMALL(Setup!$F$7:$F$16,9)>=9999999,"",INDEX(Setup!$A$7:$A$16,MATCH(SMALL(Setup!$F$7:$F$16,9),Setup!$F$7:$F$16,0))),"")
B25: 10 | C25: =IFERROR(IF(SMALL(Setup!$F$7:$F$16,10)>=9999999,"",INDEX(Setup!$A$7:$A$16,MATCH(SMALL(Setup!$F$7:$F$16,10),Setup!$F$7:$F$16,0))),"")
B33: SNOWBALL VS AVALANCHE
B34: Method | C34: Months | E34: Total interest
B35: =Setup!$F$4 | C35: =IF(SUM(Setup!$B$7:$B$16)=0,"—",IF(Engine!$A$18=0,">60",Engine!$A$18)) | E35: =SUM(Engine!$C$16:$BJ$16)
B36: =Compare!$BM$1 | C36: =IF(SUM(Setup!$B$7:$B$16)=0,"—",IF(Compare!$A$18=0,">60",Compare!$A$18)) | E36: =SUM(Compare!$C$16:$BJ$16)
B38: =IF(SUM(Setup!$B$7:$B$16)=0,"Add your debts on Setup to compare the two methods.",IF(ABS(E35-E36)<0.5,"Both methods cost about the same.",IF(E36<E35,B36&" would save you "&TEXT(E35-E36,"$#,##0")&" in interest.",B35&" saves you "&TEXT(E36-E35,"$#,##0")&" in interest against "&B36&".")))

Sheet Debt Tracker
A1: Debt Tracker
A2: Log what you've paid on each debt. Remaining and progress update themselves.
A4: Debt | B4: Original balance | C4: Paid so far | D4: Remaining | E4: % paid | F4: Min payment
A5: =IF(Setup!A7="","",Setup!A7) | B5: =IF(Setup!B7="","",Setup!B7) | C5: 640 | D5: =IF($A5="","",MAX(0,B5-C5)) | E5: =IF(OR($A5="",B5=0),"",C5/B5) | F5: =IF(Setup!D7="","",Setup!D7)
A6: =IF(Setup!A8="","",Setup!A8) | B6: =IF(Setup!B8="","",Setup!B8) | C6: 600 | D6: =IF($A6="","",MAX(0,B6-C6)) | E6: =IF(OR($A6="",B6=0),"",C6/B6) | F6: =IF(Setup!D8="","",Setup!D8)
A7: =IF(Setup!A9="","",Setup!A9) | B7: =IF(Setup!B9="","",Setup!B9) | C7: 2400 | D7: =IF($A7="","",MAX(0,B7-C7)) | E7: =IF(OR($A7="",B7=0),"",C7/B7) | F7: =IF(Setup!D9="","",Setup!D9)
A8: =IF(Setup!A10="","",Setup!A10) | B8: =IF(Setup!B10="","",Setup!B10) | C8: 1150 | D8: =IF($A8="","",MAX(0,B8-C8)) | E8: =IF(OR($A8="",B8=0),"",C8/B8) | F8: =IF(Setup!D10="","",Setup!D10)
A9: =IF(Setup!A11="","",Setup!A11) | B9: =IF(Setup!B11="","",Setup!B11) | C9: 3900 | D9: =IF($A9="","",MAX(0,B9-C9)) | E9: =IF(OR($A9="",B9=0),"",C9/B9) | F9: =IF(Setup!D11="","",Setup!D11)
A10: =IF(Setup!A12="","",Setup!A12) | B10: =IF(Setup!B12="","",Setup!B12) | C10: 2200 | D10: =IF($A10="","",MAX(0,B10-C10)) | E10: =IF(OR($A10="",B10=0),"",C10/B10) | F10: =IF(Setup!D12="","",Setup!D12)
A11: =IF(Setup!A13="","",Setup!A13) | B11: =IF(Setup!B13="","",Setup!B13) | D11: =IF($A11="","",MAX(0,B11-C11)) | E11: =IF(OR($A11="",B11=0),"",C11/B11) | F11: =IF(Setup!D13="","",Setup!D13)
A12: =IF(Setup!A14="","",Setup!A14) | B12: =IF(Setup!B14="","",Setup!B14) | D12: =IF($A12="","",MAX(0,B12-C12)) | E12: =IF(OR($A12="",B12=0),"",C12/B12) | F12: =IF(Setup!D14="","",Setup!D14)
A13: =IF(Setup!A15="","",Setup!A15) | B13: =IF(Setup!B15="","",Setup!B15) | D13: =IF($A13="","",MAX(0,B13-C13)) | E13: =IF(OR($A13="",B13=0),"",C13/B13) | F13: =IF(Setup!D15="","",Setup!D15)
A14: =IF(Setup!A16="","",Setup!A16) | B14: =IF(Setup!B16="","",Setup!B16) | D14: =IF($A14="","",MAX(0,B14-C14)) | E14: =IF(OR($A14="",B14=0),"",C14/B14) | F14: =IF(Setup!D16="","",Setup!D16)
A15: TOTAL | B15: =SUM(B5:B14) -> 0 | C15: =SUM(C5:C14) -> 0 | D15: =SUM(D5:D14) -> 0

Sheet Engine
A1: Engine — payoff simulation (Snowball / Avalanche / Custom). Do not edit. You can hide this sheet.
A2: Debt | B2: Start | C2: 1 | D2: 2 | E2: 3 | F2: 4 | G2: 5 | H2: 6 | I2: 7 | J2: 8 | K2: 9 | L2: 10 | M2: 11 | N2: 12 | O2: 13 | P2: 14 | Q2: 15 | R2: 16 | S2: 17 | T2: 18 | U2: 19 | V2: 20 | W2: 21 | X2: 22 | Y2: 23 | Z2: 24 | AA2: 25 | AB2: 26 | AC2: 27 | AD2: 28 | AE2: 29 | AF2: 30 | AG2: 31 | AH2: 32 | AI2: 33 | AJ2: 34 | AK2: 35 | AL2: 36 | AM2: 37 | AN2: 38 | AO2: 39 | AP2: 40 | AQ2: 41 | AR2: 42 | AS2: 43 | AT2: 44 | AU2: 45 | AV2: 46 | AW2: 47 | AX2: 48 | AY2: 49 | AZ2: 50 | BA2: 51 | BB2: 52 | BC2: 53 | BD2: 54 | BE2: 55 | BF2: 56 | BG2: 57 | BH2: 58 | BI2: 59 | BJ2: 60
A3: =Setup!A7 -> 0 | B3: =IF(Setup!B7="",0,Setup!B7) -> 0 | C3: =MAX(0,B3+B3*Setup!$C$7/1200-(IF(B3<=0,0,Setup!$D$7+IF(Setup!$F$7=C$14,C$13,0)))) -> 0 | D3: =MAX(0,C3+C3*Setup!$C$7/1200-(IF(C3<=0,0,Setup!$D$7+IF(Setup!$F$7=D$14,D$13,0)))) -> 0 | E3: =MAX(0,D3+D3*Setup!$C$7/1200-(IF(D3<=0,0,Setup!$D$7+IF(Setup!$F$7=E$14,E$13,0)))) -> 0 | F3: =MAX(0,E3+E3*Setup!$C$7/1200-(IF(E3<=0,0,Setup!$D$7+IF(Setup!$F$7=F$14,F$13,0)))) -> 0 | G3: =MAX(0,F3+F3*Setup!$C$7/1200-(IF(F3<=0,0,Setup!$D$7+IF(Setup!$F$7=G$14,G$13,0)))) -> 0 | H3: =MAX(0,G3+G3*Setup!$C$7/1200-(IF(G3<=0,0,Setup!$D$7+IF(Setup!$F$7=H$14,H$13,0)))) -> 0 | I3: =MAX(0,H3+H3*Setup!$C$7/1200-(IF(H3<=0,0,Setup!$D$7+IF(Setup!$F$7=I$14,I$13,0)))) -> 0 | J3: =MAX(0,I3+I3*Setup!$C$7/1200-(IF(I3<=0,0,Setup!$D$7+IF(Setup!$F$7=J$14,J$13,0)))) -> 0 | ... BJ3: =MAX(0,BI3+BI3*Setup!$C$7/1200-(IF(BI3<=0,0,Setup!$D$7+IF(Setup!$F$7=BJ$14,BJ$13,0)))) -> 0
A4: =Setup!A8 -> 0 | B4: =IF(Setup!B8="",0,Setup!B8) -> 0 | C4: =MAX(0,B4+B4*Setup!$C$8/1200-(IF(B4<=0,0,Setup!$D$8+IF(Setup!$F$8=C$14,C$13,0)))) -> 0 | D4: =MAX(0,C4+C4*Setup!$C$8/1200-(IF(C4<=0,0,Setup!$D$8+IF(Setup!$F$8=D$14,D$13,0)))) -> 0 | E4: =MAX(0,D4+D4*Setup!$C$8/1200-(IF(D4<=0,0,Setup!$D$8+IF(Setup!$F$8=E$14,E$13,0)))) -> 0 | F4: =MAX(0,E4+E4*Setup!$C$8/1200-(IF(E4<=0,0,Setup!$D$8+IF(Setup!$F$8=F$14,F$13,0)))) -> 0 | G4: =MAX(0,F4+F4*Setup!$C$8/1200-(IF(F4<=0,0,Setup!$D$8+IF(Setup!$F$8=G$14,G$13,0)))) -> 0 | H4: =MAX(0,G4+G4*Setup!$C$8/1200-(IF(G4<=0,0,Setup!$D$8+IF(Setup!$F$8=H$14,H$13,0)))) -> 0 | I4: =MAX(0,H4+H4*Setup!$C$8/1200-(IF(H4<=0,0,Setup!$D$8+IF(Setup!$F$8=I$14,I$13,0)))) -> 0 | J4: =MAX(0,I4+I4*Setup!$C$8/1200-(IF(I4<=0,0,Setup!$D$8+IF(Setup!$F$8=J$14,J$13,0)))) -> 0 | ... BJ4: =MAX(0,BI4+BI4*Setup!$C$8/1200-(IF(BI4<=0,0,Setup!$D$8+IF(Setup!$F$8=BJ$14,BJ$13,0)))) -> 0
A5: =Setup!A9 -> 0 | B5: =IF(Setup!B9="",0,Setup!B9) -> 0 | C5: =MAX(0,B5+B5*Setup!$C$9/1200-(IF(B5<=0,0,Setup!$D$9+IF(Setup!$F$9=C$14,C$13,0)))) -> 0 | D5: =MAX(0,C5+C5*Setup!$C$9/1200-(IF(C5<=0,0,Setup!$D$9+IF(Setup!$F$9=D$14,D$13,0)))) -> 0 | E5: =MAX(0,D5+D5*Setup!$C$9/1200-(IF(D5<=0,0,Setup!$D$9+IF(Setup!$F$9=E$14,E$13,0)))) -> 0 | F5: =MAX(0,E5+E5*Setup!$C$9/1200-(IF(E5<=0,0,Setup!$D$9+IF(Setup!$F$9=F$14,F$13,0)))) -> 0 | G5: =MAX(0,F5+F5*Setup!$C$9/1200-(IF(F5<=0,0,Setup!$D$9+IF(Setup!$F$9=G$14,G$13,0)))) -> 0 | H5: =MAX(0,G5+G5*Setup!$C$9/1200-(IF(G5<=0,0,Setup!$D$9+IF(Setup!$F$9=H$14,H$13,0)))) -> 0 | I5: =MAX(0,H5+H5*Setup!$C$9/1200-(IF(H5<=0,0,Setup!$D$9+IF(Setup!$F$9=I$14,I$13,0)))) -> 0 | J5: =MAX(0,I5+I5*Setup!$C$9/1200-(IF(I5<=0,0,Setup!$D$9+IF(Setup!$F$9=J$14,J$13,0)))) -> 0 | ... BJ5: =MAX(0,BI5+BI5*Setup!$C$9/1200-(IF(BI5<=0,0,Setup!$D$9+IF(Setup!$F$9=BJ$14,BJ$13,0)))) -> 0
A6: =Setup!A10 -> 0 | B6: =IF(Setup!B10="",0,Setup!B10) -> 0 | C6: =MAX(0,B6+B6*Setup!$C$10/1200-(IF(B6<=0,0,Setup!$D$10+IF(Setup!$F$10=C$14,C$13,0)))) -> 0 | D6: =MAX(0,C6+C6*Setup!$C$10/1200-(IF(C6<=0,0,Setup!$D$10+IF(Setup!$F$10=D$14,D$13,0)))) -> 0 | E6: =MAX(0,D6+D6*Setup!$C$10/1200-(IF(D6<=0,0,Setup!$D$10+IF(Setup!$F$10=E$14,E$13,0)))) -> 0 | F6: =MAX(0,E6+E6*Setup!$C$10/1200-(IF(E6<=0,0,Setup!$D$10+IF(Setup!$F$10=F$14,F$13,0)))) -> 0 | G6: =MAX(0,F6+F6*Setup!$C$10/1200-(IF(F6<=0,0,Setup!$D$10+IF(Setup!$F$10=G$14,G$13,0)))) -> 0 | H6: =MAX(0,G6+G6*Setup!$C$10/1200-(IF(G6<=0,0,Setup!$D$10+IF(Setup!$F$10=H$14,H$13,0)))) -> 0 | I6: =MAX(0,H6+H6*Setup!$C$10/1200-(IF(H6<=0,0,Setup!$D$10+IF(Setup!$F$10=I$14,I$13,0)))) -> 0 | J6: =MAX(0,I6+I6*Setup!$C$10/1200-(IF(I6<=0,0,Setup!$D$10+IF(Setup!$F$10=J$14,J$13,0)))) -> 0 | ... BJ6: =MAX(0,BI6+BI6*Setup!$C$10/1200-(IF(BI6<=0,0,Setup!$D$10+IF(Setup!$F$10=BJ$14,BJ$13,0)))) -> 0
A7: =Setup!A11 -> 0 | B7: =IF(Setup!B11="",0,Setup!B11) -> 0 | C7: =MAX(0,B7+B7*Setup!$C$11/1200-(IF(B7<=0,0,Setup!$D$11+IF(Setup!$F$11=C$14,C$13,0)))) -> 0 | D7: =MAX(0,C7+C7*Setup!$C$11/1200-(IF(C7<=0,0,Setup!$D$11+IF(Setup!$F$11=D$14,D$13,0)))) -> 0 | E7: =MAX(0,D7+D7*Setup!$C$11/1200-(IF(D7<=0,0,Setup!$D$11+IF(Setup!$F$11=E$14,E$13,0)))) -> 0 | F7: =MAX(0,E7+E7*Setup!$C$11/1200-(IF(E7<=0,0,Setup!$D$11+IF(Setup!$F$11=F$14,F$13,0)))) -> 0 | G7: =MAX(0,F7+F7*Setup!$C$11/1200-(IF(F7<=0,0,Setup!$D$11+IF(Setup!$F$11=G$14,G$13,0)))) -> 0 | H7: =MAX(0,G7+G7*Setup!$C$11/1200-(IF(G7<=0,0,Setup!$D$11+IF(Setup!$F$11=H$14,H$13,0)))) -> 0 | I7: =MAX(0,H7+H7*Setup!$C$11/1200-(IF(H7<=0,0,Setup!$D$11+IF(Setup!$F$11=I$14,I$13,0)))) -> 0 | J7: =MAX(0,I7+I7*Setup!$C$11/1200-(IF(I7<=0,0,Setup!$D$11+IF(Setup!$F$11=J$14,J$13,0)))) -> 0 | ... BJ7: =MAX(0,BI7+BI7*Setup!$C$11/1200-(IF(BI7<=0,0,Setup!$D$11+IF(Setup!$F$11=BJ$14,BJ$13,0)))) -> 0
A8: =Setup!A12 -> 0 | B8: =IF(Setup!B12="",0,Setup!B12) -> 0 | C8: =MAX(0,B8+B8*Setup!$C$12/1200-(IF(B8<=0,0,Setup!$D$12+IF(Setup!$F$12=C$14,C$13,0)))) -> 0 | D8: =MAX(0,C8+C8*Setup!$C$12/1200-(IF(C8<=0,0,Setup!$D$12+IF(Setup!$F$12=D$14,D$13,0)))) -> 0 | E8: =MAX(0,D8+D8*Setup!$C$12/1200-(IF(D8<=0,0,Setup!$D$12+IF(Setup!$F$12=E$14,E$13,0)))) -> 0 | F8: =MAX(0,E8+E8*Setup!$C$12/1200-(IF(E8<=0,0,Setup!$D$12+IF(Setup!$F$12=F$14,F$13,0)))) -> 0 | G8: =MAX(0,F8+F8*Setup!$C$12/1200-(IF(F8<=0,0,Setup!$D$12+IF(Setup!$F$12=G$14,G$13,0)))) -> 0 | H8: =MAX(0,G8+G8*Setup!$C$12/1200-(IF(G8<=0,0,Setup!$D$12+IF(Setup!$F$12=H$14,H$13,0)))) -> 0 | I8: =MAX(0,H8+H8*Setup!$C$12/1200-(IF(H8<=0,0,Setup!$D$12+IF(Setup!$F$12=I$14,I$13,0)))) -> 0 | J8: =MAX(0,I8+I8*Setup!$C$12/1200-(IF(I8<=0,0,Setup!$D$12+IF(Setup!$F$12=J$14,J$13,0)))) -> 0 | ... BJ8: =MAX(0,BI8+BI8*Setup!$C$12/1200-(IF(BI8<=0,0,Setup!$D$12+IF(Setup!$F$12=BJ$14,BJ$13,0)))) -> 0
A9: =Setup!A13 -> 0 | B9: =IF(Setup!B13="",0,Setup!B13) -> 0 | C9: =MAX(0,B9+B9*Setup!$C$13/1200-(IF(B9<=0,0,Setup!$D$13+IF(Setup!$F$13=C$14,C$13,0)))) -> 0 | D9: =MAX(0,C9+C9*Setup!$C$13/1200-(IF(C9<=0,0,Setup!$D$13+IF(Setup!$F$13=D$14,D$13,0)))) -> 0 | E9: =MAX(0,D9+D9*Setup!$C$13/1200-(IF(D9<=0,0,Setup!$D$13+IF(Setup!$F$13=E$14,E$13,0)))) -> 0 | F9: =MAX(0,E9+E9*Setup!$C$13/1200-(IF(E9<=0,0,Setup!$D$13+IF(Setup!$F$13=F$14,F$13,0)))) -> 0 | G9: =MAX(0,F9+F9*Setup!$C$13/1200-(IF(F9<=0,0,Setup!$D$13+IF(Setup!$F$13=G$14,G$13,0)))) -> 0 | H9: =MAX(0,G9+G9*Setup!$C$13/1200-(IF(G9<=0,0,Setup!$D$13+IF(Setup!$F$13=H$14,H$13,0)))) -> 0 | I9: =MAX(0,H9+H9*Setup!$C$13/1200-(IF(H9<=0,0,Setup!$D$13+IF(Setup!$F$13=I$14,I$13,0)))) -> 0 | J9: =MAX(0,I9+I9*Setup!$C$13/1200-(IF(I9<=0,0,Setup!$D$13+IF(Setup!$F$13=J$14,J$13,0)))) -> 0 | ... BJ9: =MAX(0,BI9+BI9*Setup!$C$13/1200-(IF(BI9<=0,0,Setup!$D$13+IF(Setup!$F$13=BJ$14,BJ$13,0)))) -> 0
A10: =Setup!A14 -> 0 | B10: =IF(Setup!B14="",0,Setup!B14) -> 0 | C10: =MAX(0,B10+B10*Setup!$C$14/1200-(IF(B10<=0,0,Setup!$D$14+IF(Setup!$F$14=C$14,C$13,0)))) -> 0 | D10: =MAX(0,C10+C10*Setup!$C$14/1200-(IF(C10<=0,0,Setup!$D$14+IF(Setup!$F$14=D$14,D$13,0)))) -> 0 | E10: =MAX(0,D10+D10*Setup!$C$14/1200-(IF(D10<=0,0,Setup!$D$14+IF(Setup!$F$14=E$14,E$13,0)))) -> 0 | F10: =MAX(0,E10+E10*Setup!$C$14/1200-(IF(E10<=0,0,Setup!$D$14+IF(Setup!$F$14=F$14,F$13,0)))) -> 0 | G10: =MAX(0,F10+F10*Setup!$C$14/1200-(IF(F10<=0,0,Setup!$D$14+IF(Setup!$F$14=G$14,G$13,0)))) -> 0 | H10: =MAX(0,G10+G10*Setup!$C$14/1200-(IF(G10<=0,0,Setup!$D$14+IF(Setup!$F$14=H$14,H$13,0)))) -> 0 | I10: =MAX(0,H10+H10*Setup!$C$14/1200-(IF(H10<=0,0,Setup!$D$14+IF(Setup!$F$14=I$14,I$13,0)))) -> 0 | J10: =MAX(0,I10+I10*Setup!$C$14/1200-(IF(I10<=0,0,Setup!$D$14+IF(Setup!$F$14=J$14,J$13,0)))) -> 0 | ... BJ10: =MAX(0,BI10+BI10*Setup!$C$14/1200-(IF(BI10<=0,0,Setup!$D$14+IF(Setup!$F$14=BJ$14,BJ$13,0)))) -> 0
A11: =Setup!A15 -> 0 | B11: =IF(Setup!B15="",0,Setup!B15) -> 0 | C11: =MAX(0,B11+B11*Setup!$C$15/1200-(IF(B11<=0,0,Setup!$D$15+IF(Setup!$F$15=C$14,C$13,0)))) -> 0 | D11: =MAX(0,C11+C11*Setup!$C$15/1200-(IF(C11<=0,0,Setup!$D$15+IF(Setup!$F$15=D$14,D$13,0)))) -> 0 | E11: =MAX(0,D11+D11*Setup!$C$15/1200-(IF(D11<=0,0,Setup!$D$15+IF(Setup!$F$15=E$14,E$13,0)))) -> 0 | F11: =MAX(0,E11+E11*Setup!$C$15/1200-(IF(E11<=0,0,Setup!$D$15+IF(Setup!$F$15=F$14,F$13,0)))) -> 0 | G11: =MAX(0,F11+F11*Setup!$C$15/1200-(IF(F11<=0,0,Setup!$D$15+IF(Setup!$F$15=G$14,G$13,0)))) -> 0 | H11: =MAX(0,G11+G11*Setup!$C$15/1200-(IF(G11<=0,0,Setup!$D$15+IF(Setup!$F$15=H$14,H$13,0)))) -> 0 | I11: =MAX(0,H11+H11*Setup!$C$15/1200-(IF(H11<=0,0,Setup!$D$15+IF(Setup!$F$15=I$14,I$13,0)))) -> 0 | J11: =MAX(0,I11+I11*Setup!$C$15/1200-(IF(I11<=0,0,Setup!$D$15+IF(Setup!$F$15=J$14,J$13,0)))) -> 0 | ... BJ11: =MAX(0,BI11+BI11*Setup!$C$15/1200-(IF(BI11<=0,0,Setup!$D$15+IF(Setup!$F$15=BJ$14,BJ$13,0)))) -> 0
A12: =Setup!A16 -> 0 | B12: =IF(Setup!B16="",0,Setup!B16) -> 0 | C12: =MAX(0,B12+B12*Setup!$C$16/1200-(IF(B12<=0,0,Setup!$D$16+IF(Setup!$F$16=C$14,C$13,0)))) -> 0 | D12: =MAX(0,C12+C12*Setup!$C$16/1200-(IF(C12<=0,0,Setup!$D$16+IF(Setup!$F$16=D$14,D$13,0)))) -> 0 | E12: =MAX(0,D12+D12*Setup!$C$16/1200-(IF(D12<=0,0,Setup!$D$16+IF(Setup!$F$16=E$14,E$13,0)))) -> 0 | F12: =MAX(0,E12+E12*Setup!$C$16/1200-(IF(E12<=0,0,Setup!$D$16+IF(Setup!$F$16=F$14,F$13,0)))) -> 0 | G12: =MAX(0,F12+F12*Setup!$C$16/1200-(IF(F12<=0,0,Setup!$D$16+IF(Setup!$F$16=G$14,G$13,0)))) -> 0 | H12: =MAX(0,G12+G12*Setup!$C$16/1200-(IF(G12<=0,0,Setup!$D$16+IF(Setup!$F$16=H$14,H$13,0)))) -> 0 | I12: =MAX(0,H12+H12*Setup!$C$16/1200-(IF(H12<=0,0,Setup!$D$16+IF(Setup!$F$16=I$14,I$13,0)))) -> 0 | J12: =MAX(0,I12+I12*Setup!$C$16/1200-(IF(I12<=0,0,Setup!$D$16+IF(Setup!$F$16=J$14,J$13,0)))) -> 0 | ... BJ12: =MAX(0,BI12+BI12*Setup!$C$16/1200-(IF(BI12<=0,0,Setup!$D$16+IF(Setup!$F$16=BJ$14,BJ$13,0)))) -> 0
A13: pool | C13: =Setup!$I$4+SUMIFS(Setup!$D$7:$D$16,Engine!$B$3:$B$12,"=0") -> 0 | D13: =Setup!$I$4+SUMIFS(Setup!$D$7:$D$16,Engine!$C$3:$C$12,"=0") -> 0 | E13: =Setup!$I$4+SUMIFS(Setup!$D$7:$D$16,Engine!$D$3:$D$12,"=0") -> 0 | F13: =Setup!$I$4+SUMIFS(Setup!$D$7:$D$16,Engine!$E$3:$E$12,"=0") -> 0 | G13: =Setup!$I$4+SUMIFS(Setup!$D$7:$D$16,Engine!$F$3:$F$12,"=0") -> 0 | H13: =Setup!$I$4+SUMIFS(Setup!$D$7:$D$16,Engine!$G$3:$G$12,"=0") -> 0 | I13: =Setup!$I$4+SUMIFS(Setup!$D$7:$D$16,Engine!$H$3:$H$12,"=0") -> 0 | J13: =Setup!$I$4+SUMIFS(Setup!$D$7:$D$16,Engine!$I$3:$I$12,"=0") -> 0 | K13: =Setup!$I$4+SUMIFS(Setup!$D$7:$D$16,Engine!$J$3:$J$12,"=0") -> 0 | L13: =Setup!$I$4+SUMIFS(Setup!$D$7:$D$16,Engine!$K$3:$K$12,"=0") -> 0 | M13: =Setup!$I$4+SUMIFS(Setup!$D$7:$D$16,Engine!$L$3:$L$12,"=0") -> 0 | N13: =Setup!$I$4+SUMIFS(Setup!$D$7:$D$16,Engine!$M$3:$M$12,"=0") -> 0 | O13: =Setup!$I$4+SUMIFS(Setup!$D$7:$D$16,Engine!$N$3:$N$12,"=0") -> 0 | P13: =Setup!$I$4+SUMIFS(Setup!$D$7:$D$16,Engine!$O$3:$O$12,"=0") -> 0 | Q13: =Setup!$I$4+SUMIFS(Setup!$D$7:$D$16,Engine!$P$3:$P$12,"=0") -> 0 | R13: =Setup!$I$4+SUMIFS(Setup!$D$7:$D$16,Engine!$Q$3:$Q$12,"=0") -> 0 | S13: =Setup!$I$4+SUMIFS(Setup!$D$7:$D$16,Engine!$R$3:$R$12,"=0") -> 0 | T13: =Setup!$I$4+SUMIFS(Setup!$D$7:$D$16,Engine!$S$3:$S$12,"=0") -> 0 | U13: =Setup!$I$4+SUMIFS(Setup!$D$7:$D$16,Engine!$T$3:$T$12,"=0") -> 0 | V13: =Setup!$I$4+SUMIFS(Setup!$D$7:$D$16,Engine!$U$3:$U$12,"=0") -> 0 | W13: =Setup!$I$4+SUMIFS(Setup!$D$7:$D$16,Engine!$V$3:$V$12,"=0") -> 0 | X13: =Setup!$I$4+SUMIFS(Setup!$D$7:$D$16,Engine!$W$3:$W$12,"=0") -> 0 | Y13: =Setup!$I$4+SUMIFS(Setup!$D$7:$D$16,Engine!$X$3:$X$12,"=0") -> 0 | Z13: =Setup!$I$4+SUMIFS(Setup!$D$7:$D$16,Engine!$Y$3:$Y$12,"=0") -> 0 | AA13: =Setup!$I$4+SUMIFS(Setup!$D$7:$D$16,Engine!$Z$3:$Z$12,"=0") -> 0 | AB13: =Setup!$I$4+SUMIFS(Setup!$D$7:$D$16,Engine!$AA$3:$AA$12,"=0") -> 0 | AC13: =Setup!$I$4+SUMIFS(Setup!$D$7:$D$16,Engine!$AB$3:$AB$12,"=0") -> 0 | AD13: =Setup!$I$4+SUMIFS(Setup!$D$7:$D$16,Engine!$AC$3:$AC$12,"=0") -> 0 | AE13: =Setup!$I$4+SUMIFS(Setup!$D$7:$D$16,Engine!$AD$3:$AD$12,"=0") -> 0 | AF13: =Setup!$I$4+SUMIFS(Setup!$D$7:$D$16,Engine!$AE$3:$AE$12,"=0") -> 0 | AG13: =Setup!$I$4+SUMIFS(Setup!$D$7:$D$16,Engine!$AF$3:$AF$12,"=0") -> 0 | AH13: =Setup!$I$4+SUMIFS(Setup!$D$7:$D$16,Engine!$AG$3:$AG$12,"=0") -> 0 | AI13: =Setup!$I$4+SUMIFS(Setup!$D$7:$D$16,Engine!$AH$3:$AH$12,"=0") -> 0 | AJ13: =Setup!$I$4+SUMIFS(Setup!$D$7:$D$16,Engine!$AI$3:$AI$12,"=0") -> 0 | AK13: =Setup!$I$4+SUMIFS(Setup!$D$7:$D$16,Engine!$AJ$3:$AJ$12,"=0") -> 0 | AL13: =Setup!$I$4+SUMIFS(Setup!$D$7:$D$16,Engine!$AK$3:$AK$12,"=0") -> 0 | AM13: =Setup!$I$4+SUMIFS(Setup!$D$7:$D$16,Engine!$AL$3:$AL$12,"=0") -> 0 | AN13: =Setup!$I$4+SUMIFS(Setup!$D$7:$D$16,Engine!$AM$3:$AM$12,"=0") -> 0 | AO13: =Setup!$I$4+SUMIFS(Setup!$D$7:$D$16,Engine!$AN$3:$AN$12,"=0") -> 0 | AP13: =Setup!$I$4+SUMIFS(Setup!$D$7:$D$16,Engine!$AO$3:$AO$12,"=0") -> 0 | AQ13: =Setup!$I$4+SUMIFS(Setup!$D$7:$D$16,Engine!$AP$3:$AP$12,"=0") -> 0 | AR13: =Setup!$I$4+SUMIFS(Setup!$D$7:$D$16,Engine!$AQ$3:$AQ$12,"=0") -> 0 | AS13: =Setup!$I$4+SUMIFS(Setup!$D$7:$D$16,Engine!$AR$3:$AR$12,"=0") -> 0 | AT13: =Setup!$I$4+SUMIFS(Setup!$D$7:$D$16,Engine!$AS$3:$AS$12,"=0") -> 0 | AU13: =Setup!$I$4+SUMIFS(Setup!$D$7:$D$16,Engine!$AT$3:$AT$12,"=0") -> 0 | AV13: =Setup!$I$4+SUMIFS(Setup!$D$7:$D$16,Engine!$AU$3:$AU$12,"=0") -> 0 | AW13: =Setup!$I$4+SUMIFS(Setup!$D$7:$D$16,Engine!$AV$3:$AV$12,"=0") -> 0 | AX13: =Setup!$I$4+SUMIFS(Setup!$D$7:$D$16,Engine!$AW$3:$AW$12,"=0") -> 0 | AY13: =Setup!$I$4+SUMIFS(Setup!$D$7:$D$16,Engine!$AX$3:$AX$12,"=0") -> 0 | AZ13: =Setup!$I$4+SUMIFS(Setup!$D$7:$D$16,Engine!$AY$3:$AY$12,"=0") -> 0 | BA13: =Setup!$I$4+SUMIFS(Setup!$D$7:$D$16,Engine!$AZ$3:$AZ$12,"=0") -> 0 | BB13: =Setup!$I$4+SUMIFS(Setup!$D$7:$D$16,Engine!$BA$3:$BA$12,"=0") -> 0 | BC13: =Setup!$I$4+SUMIFS(Setup!$D$7:$D$16,Engine!$BB$3:$BB$12,"=0") -> 0 | BD13: =Setup!$I$4+SUMIFS(Setup!$D$7:$D$16,Engine!$BC$3:$BC$12,"=0") -> 0 | BE13: =Setup!$I$4+SUMIFS(Setup!$D$7:$D$16,Engine!$BD$3:$BD$12,"=0") -> 0 | BF13: =Setup!$I$4+SUMIFS(Setup!$D$7:$D$16,Engine!$BE$3:$BE$12,"=0") -> 0 | BG13: =Setup!$I$4+SUMIFS(Setup!$D$7:$D$16,Engine!$BF$3:$BF$12,"=0") -> 0 | BH13: =Setup!$I$4+SUMIFS(Setup!$D$7:$D$16,Engine!$BG$3:$BG$12,"=0") -> 0 | BI13: =Setup!$I$4+SUMIFS(Setup!$D$7:$D$16,Engine!$BH$3:$BH$12,"=0") -> 0 | BJ13: =Setup!$I$4+SUMIFS(Setup!$D$7:$D$16,Engine!$BI$3:$BI$12,"=0") -> 0
A14: priority score | C14: =_xlfn.MINIFS(Setup!$F$7:$F$16,Engine!$B$3:$B$12,">0") -> 0 | D14: =_xlfn.MINIFS(Setup!$F$7:$F$16,Engine!$C$3:$C$12,">0") -> 0 | E14: =_xlfn.MINIFS(Setup!$F$7:$F$16,Engine!$D$3:$D$12,">0") -> 0 | F14: =_xlfn.MINIFS(Setup!$F$7:$F$16,Engine!$E$3:$E$12,">0") -> 0 | G14: =_xlfn.MINIFS(Setup!$F$7:$F$16,Engine!$F$3:$F$12,">0") -> 0 | H14: =_xlfn.MINIFS(Setup!$F$7:$F$16,Engine!$G$3:$G$12,">0") -> 0 | I14: =_xlfn.MINIFS(Setup!$F$7:$F$16,Engine!$H$3:$H$12,">0") -> 0 | J14: =_xlfn.MINIFS(Setup!$F$7:$F$16,Engine!$I$3:$I$12,">0") -> 0 | K14: =_xlfn.MINIFS(Setup!$F$7:$F$16,Engine!$J$3:$J$12,">0") -> 0 | L14: =_xlfn.MINIFS(Setup!$F$7:$F$16,Engine!$K$3:$K$12,">0") -> 0 | M14: =_xlfn.MINIFS(Setup!$F$7:$F$16,Engine!$L$3:$L$12,">0") -> 0 | N14: =_xlfn.MINIFS(Setup!$F$7:$F$16,Engine!$M$3:$M$12,">0") -> 0 | O14: =_xlfn.MINIFS(Setup!$F$7:$F$16,Engine!$N$3:$N$12,">0") -> 0 | P14: =_xlfn.MINIFS(Setup!$F$7:$F$16,Engine!$O$3:$O$12,">0") -> 0 | Q14: =_xlfn.MINIFS(Setup!$F$7:$F$16,Engine!$P$3:$P$12,">0") -> 0 | R14: =_xlfn.MINIFS(Setup!$F$7:$F$16,Engine!$Q$3:$Q$12,">0") -> 0 | S14: =_xlfn.MINIFS(Setup!$F$7:$F$16,Engine!$R$3:$R$12,">0") -> 0 | T14: =_xlfn.MINIFS(Setup!$F$7:$F$16,Engine!$S$3:$S$12,">0") -> 0 | U14: =_xlfn.MINIFS(Setup!$F$7:$F$16,Engine!$T$3:$T$12,">0") -> 0 | V14: =_xlfn.MINIFS(Setup!$F$7:$F$16,Engine!$U$3:$U$12,">0") -> 0 | W14: =_xlfn.MINIFS(Setup!$F$7:$F$16,Engine!$V$3:$V$12,">0") -> 0 | X14: =_xlfn.MINIFS(Setup!$F$7:$F$16,Engine!$W$3:$W$12,">0") -> 0 | Y14: =_xlfn.MINIFS(Setup!$F$7:$F$16,Engine!$X$3:$X$12,">0") -> 0 | Z14: =_xlfn.MINIFS(Setup!$F$7:$F$16,Engine!$Y$3:$Y$12,">0") -> 0 | AA14: =_xlfn.MINIFS(Setup!$F$7:$F$16,Engine!$Z$3:$Z$12,">0") -> 0 | AB14: =_xlfn.MINIFS(Setup!$F$7:$F$16,Engine!$AA$3:$AA$12,">0") -> 0 | AC14: =_xlfn.MINIFS(Setup!$F$7:$F$16,Engine!$AB$3:$AB$12,">0") -> 0 | AD14: =_xlfn.MINIFS(Setup!$F$7:$F$16,Engine!$AC$3:$AC$12,">0") -> 0 | AE14: =_xlfn.MINIFS(Setup!$F$7:$F$16,Engine!$AD$3:$AD$12,">0") -> 0 | AF14: =_xlfn.MINIFS(Setup!$F$7:$F$16,Engine!$AE$3:$AE$12,">0") -> 0 | AG14: =_xlfn.MINIFS(Setup!$F$7:$F$16,Engine!$AF$3:$AF$12,">0") -> 0 | AH14: =_xlfn.MINIFS(Setup!$F$7:$F$16,Engine!$AG$3:$AG$12,">0") -> 0 | AI14: =_xlfn.MINIFS(Setup!$F$7:$F$16,Engine!$AH$3:$AH$12,">0") -> 0 | AJ14: =_xlfn.MINIFS(Setup!$F$7:$F$16,Engine!$AI$3:$AI$12,">0") -> 0 | AK14: =_xlfn.MINIFS(Setup!$F$7:$F$16,Engine!$AJ$3:$AJ$12,">0") -> 0 | AL14: =_xlfn.MINIFS(Setup!$F$7:$F$16,Engine!$AK$3:$AK$12,">0") -> 0 | AM14: =_xlfn.MINIFS(Setup!$F$7:$F$16,Engine!$AL$3:$AL$12,">0") -> 0 | AN14: =_xlfn.MINIFS(Setup!$F$7:$F$16,Engine!$AM$3:$AM$12,">0") -> 0 | AO14: =_xlfn.MINIFS(Setup!$F$7:$F$16,Engine!$AN$3:$AN$12,">0") -> 0 | AP14: =_xlfn.MINIFS(Setup!$F$7:$F$16,Engine!$AO$3:$AO$12,">0") -> 0 | AQ14: =_xlfn.MINIFS(Setup!$F$7:$F$16,Engine!$AP$3:$AP$12,">0") -> 0 | AR14: =_xlfn.MINIFS(Setup!$F$7:$F$16,Engine!$AQ$3:$AQ$12,">0") -> 0 | AS14: =_xlfn.MINIFS(Setup!$F$7:$F$16,Engine!$AR$3:$AR$12,">0") -> 0 | AT14: =_xlfn.MINIFS(Setup!$F$7:$F$16,Engine!$AS$3:$AS$12,">0") -> 0 | AU14: =_xlfn.MINIFS(Setup!$F$7:$F$16,Engine!$AT$3:$AT$12,">0") -> 0 | AV14: =_xlfn.MINIFS(Setup!$F$7:$F$16,Engine!$AU$3:$AU$12,">0") -> 0 | AW14: =_xlfn.MINIFS(Setup!$F$7:$F$16,Engine!$AV$3:$AV$12,">0") -> 0 | AX14: =_xlfn.MINIFS(Setup!$F$7:$F$16,Engine!$AW$3:$AW$12,">0") -> 0 | AY14: =_xlfn.MINIFS(Setup!$F$7:$F$16,Engine!$AX$3:$AX$12,">0") -> 0 | AZ14: =_xlfn.MINIFS(Setup!$F$7:$F$16,Engine!$AY$3:$AY$12,">0") -> 0 | BA14: =_xlfn.MINIFS(Setup!$F$7:$F$16,Engine!$AZ$3:$AZ$12,">0") -> 0 | BB14: =_xlfn.MINIFS(Setup!$F$7:$F$16,Engine!$BA$3:$BA$12,">0") -> 0 | BC14: =_xlfn.MINIFS(Setup!$F$7:$F$16,Engine!$BB$3:$BB$12,">0") -> 0 | BD14: =_xlfn.MINIFS(Setup!$F$7:$F$16,Engine!$BC$3:$BC$12,">0") -> 0 | BE14: =_xlfn.MINIFS(Setup!$F$7:$F$16,Engine!$BD$3:$BD$12,">0") -> 0 | BF14: =_xlfn.MINIFS(Setup!$F$7:$F$16,Engine!$BE$3:$BE$12,">0") -> 0 | BG14: =_xlfn.MINIFS(Setup!$F$7:$F$16,Engine!$BF$3:$BF$12,">0") -> 0 | BH14: =_xlfn.MINIFS(Setup!$F$7:$F$16,Engine!$BG$3:$BG$12,">0") -> 0 | BI14: =_xlfn.MINIFS(Setup!$F$7:$F$16,Engine!$BH$3:$BH$12,">0") -> 0 | BJ14: =_xlfn.MINIFS(Setup!$F$7:$F$16,Engine!$BI$3:$BI$12,">0") -> 0
A15: total balance | B15: =SUM(B3:B12) -> 0 | C15: =SUM(C3:C12) -> 0 | D15: =SUM(D3:D12) -> 0 | E15: =SUM(E3:E12) -> 0 | F15: =SUM(F3:F12) -> 0 | G15: =SUM(G3:G12) -> 0 | H15: =SUM(H3:H12) -> 0 | I15: =SUM(I3:I12) -> 0 | ... BJ15: =SUM(BJ3:BJ12) -> 0
A16: interest | C16: =SUMPRODUCT(Engine!$B$3:$B$12,Setup!$C$7:$C$16)/1200 -> 0 | D16: =SUMPRODUCT(Engine!$C$3:$C$12,Setup!$C$7:$C$16)/1200 -> 0 | E16: =SUMPRODUCT(Engine!$D$3:$D$12,Setup!$C$7:$C$16)/1200 -> 0 | F16: =SUMPRODUCT(Engine!$E$3:$E$12,Setup!$C$7:$C$16)/1200 -> 0 | G16: =SUMPRODUCT(Engine!$F$3:$F$12,Setup!$C$7:$C$16)/1200 -> 0 | H16: =SUMPRODUCT(Engine!$G$3:$G$12,Setup!$C$7:$C$16)/1200 -> 0 | I16: =SUMPRODUCT(Engine!$H$3:$H$12,Setup!$C$7:$C$16)/1200 -> 0 | J16: =SUMPRODUCT(Engine!$I$3:$I$12,Setup!$C$7:$C$16)/1200 -> 0 | K16: =SUMPRODUCT(Engine!$J$3:$J$12,Setup!$C$7:$C$16)/1200 -> 0 | L16: =SUMPRODUCT(Engine!$K$3:$K$12,Setup!$C$7:$C$16)/1200 -> 0 | M16: =SUMPRODUCT(Engine!$L$3:$L$12,Setup!$C$7:$C$16)/1200 -> 0 | N16: =SUMPRODUCT(Engine!$M$3:$M$12,Setup!$C$7:$C$16)/1200 -> 0 | O16: =SUMPRODUCT(Engine!$N$3:$N$12,Setup!$C$7:$C$16)/1200 -> 0 | P16: =SUMPRODUCT(Engine!$O$3:$O$12,Setup!$C$7:$C$16)/1200 -> 0 | Q16: =SUMPRODUCT(Engine!$P$3:$P$12,Setup!$C$7:$C$16)/1200 -> 0 | R16: =SUMPRODUCT(Engine!$Q$3:$Q$12,Setup!$C$7:$C$16)/1200 -> 0 | S16: =SUMPRODUCT(Engine!$R$3:$R$12,Setup!$C$7:$C$16)/1200 -> 0 | T16: =SUMPRODUCT(Engine!$S$3:$S$12,Setup!$C$7:$C$16)/1200 -> 0 | U16: =SUMPRODUCT(Engine!$T$3:$T$12,Setup!$C$7:$C$16)/1200 -> 0 | V16: =SUMPRODUCT(Engine!$U$3:$U$12,Setup!$C$7:$C$16)/1200 -> 0 | W16: =SUMPRODUCT(Engine!$V$3:$V$12,Setup!$C$7:$C$16)/1200 -> 0 | X16: =SUMPRODUCT(Engine!$W$3:$W$12,Setup!$C$7:$C$16)/1200 -> 0 | Y16: =SUMPRODUCT(Engine!$X$3:$X$12,Setup!$C$7:$C$16)/1200 -> 0 | Z16: =SUMPRODUCT(Engine!$Y$3:$Y$12,Setup!$C$7:$C$16)/1200 -> 0 | AA16: =SUMPRODUCT(Engine!$Z$3:$Z$12,Setup!$C$7:$C$16)/1200 -> 0 | AB16: =SUMPRODUCT(Engine!$AA$3:$AA$12,Setup!$C$7:$C$16)/1200 -> 0 | AC16: =SUMPRODUCT(Engine!$AB$3:$AB$12,Setup!$C$7:$C$16)/1200 -> 0 | AD16: =SUMPRODUCT(Engine!$AC$3:$AC$12,Setup!$C$7:$C$16)/1200 -> 0 | AE16: =SUMPRODUCT(Engine!$AD$3:$AD$12,Setup!$C$7:$C$16)/1200 -> 0 | AF16: =SUMPRODUCT(Engine!$AE$3:$AE$12,Setup!$C$7:$C$16)/1200 -> 0 | AG16: =SUMPRODUCT(Engine!$AF$3:$AF$12,Setup!$C$7:$C$16)/1200 -> 0 | AH16: =SUMPRODUCT(Engine!$AG$3:$AG$12,Setup!$C$7:$C$16)/1200 -> 0 | AI16: =SUMPRODUCT(Engine!$AH$3:$AH$12,Setup!$C$7:$C$16)/1200 -> 0 | AJ16: =SUMPRODUCT(Engine!$AI$3:$AI$12,Setup!$C$7:$C$16)/1200 -> 0 | AK16: =SUMPRODUCT(Engine!$AJ$3:$AJ$12,Setup!$C$7:$C$16)/1200 -> 0 | AL16: =SUMPRODUCT(Engine!$AK$3:$AK$12,Setup!$C$7:$C$16)/1200 -> 0 | AM16: =SUMPRODUCT(Engine!$AL$3:$AL$12,Setup!$C$7:$C$16)/1200 -> 0 | AN16: =SUMPRODUCT(Engine!$AM$3:$AM$12,Setup!$C$7:$C$16)/1200 -> 0 | AO16: =SUMPRODUCT(Engine!$AN$3:$AN$12,Setup!$C$7:$C$16)/1200 -> 0 | AP16: =SUMPRODUCT(Engine!$AO$3:$AO$12,Setup!$C$7:$C$16)/1200 -> 0 | AQ16: =SUMPRODUCT(Engine!$AP$3:$AP$12,Setup!$C$7:$C$16)/1200 -> 0 | AR16: =SUMPRODUCT(Engine!$AQ$3:$AQ$12,Setup!$C$7:$C$16)/1200 -> 0 | AS16: =SUMPRODUCT(Engine!$AR$3:$AR$12,Setup!$C$7:$C$16)/1200 -> 0 | AT16: =SUMPRODUCT(Engine!$AS$3:$AS$12,Setup!$C$7:$C$16)/1200 -> 0 | AU16: =SUMPRODUCT(Engine!$AT$3:$AT$12,Setup!$C$7:$C$16)/1200 -> 0 | AV16: =SUMPRODUCT(Engine!$AU$3:$AU$12,Setup!$C$7:$C$16)/1200 -> 0 | AW16: =SUMPRODUCT(Engine!$AV$3:$AV$12,Setup!$C$7:$C$16)/1200 -> 0 | AX16: =SUMPRODUCT(Engine!$AW$3:$AW$12,Setup!$C$7:$C$16)/1200 -> 0 | AY16: =SUMPRODUCT(Engine!$AX$3:$AX$12,Setup!$C$7:$C$16)/1200 -> 0 | AZ16: =SUMPRODUCT(Engine!$AY$3:$AY$12,Setup!$C$7:$C$16)/1200 -> 0 | BA16: =SUMPRODUCT(Engine!$AZ$3:$AZ$12,Setup!$C$7:$C$16)/1200 -> 0 | BB16: =SUMPRODUCT(Engine!$BA$3:$BA$12,Setup!$C$7:$C$16)/1200 -> 0 | BC16: =SUMPRODUCT(Engine!$BB$3:$BB$12,Setup!$C$7:$C$16)/1200 -> 0 | BD16: =SUMPRODUCT(Engine!$BC$3:$BC$12,Setup!$C$7:$C$16)/1200 -> 0 | BE16: =SUMPRODUCT(Engine!$BD$3:$BD$12,Setup!$C$7:$C$16)/1200 -> 0 | BF16: =SUMPRODUCT(Engine!$BE$3:$BE$12,Setup!$C$7:$C$16)/1200 -> 0 | BG16: =SUMPRODUCT(Engine!$BF$3:$BF$12,Setup!$C$7:$C$16)/1200 -> 0 | BH16: =SUMPRODUCT(Engine!$BG$3:$BG$12,Setup!$C$7:$C$16)/1200 -> 0 | BI16: =SUMPRODUCT(Engine!$BH$3:$BH$12,Setup!$C$7:$C$16)/1200 -> 0 | BJ16: =SUMPRODUCT(Engine!$BI$3:$BI$12,Setup!$C$7:$C$16)/1200 -> 0
A18: =IFERROR(MATCH(0,Engine!$C$15:$BJ$15,0),0) -> 1 | B18: months to debt-free (helper)

Sheet Compare
A1: Compare — the same debts run through the other method, so the Dashboard can show which one costs less. Do not edit. | BM1: =IF(Setup!$F$4="Avalanche","Snowball","Avalanche")
A3: =Setup!A7 | B3: =IF(Setup!B7="",0,Setup!B7) | C3: =MAX(0,B3+B3*Setup!$C$7/1200-(IF(B3<=0,0,Setup!$D$7+IF($BL3=C$14,C$13,0)))) | D3: =MAX(0,C3+C3*Setup!$C$7/1200-(IF(C3<=0,0,Setup!$D$7+IF($BL3=D$14,D$13,0)))) | E3: =MAX(0,D3+D3*Setup!$C$7/1200-(IF(D3<=0,0,Setup!$D$7+IF($BL3=E$14,E$13,0)))) | F3: =MAX(0,E3+E3*Setup!$C$7/1200-(IF(E3<=0,0,Setup!$D$7+IF($BL3=F$14,F$13,0)))) | G3: =MAX(0,F3+F3*Setup!$C$7/1200-(IF(F3<=0,0,Setup!$D$7+IF($BL3=G$14,G$13,0)))) | H3: =MAX(0,G3+G3*Setup!$C$7/1200-(IF(G3<=0,0,Setup!$D$7+IF($BL3=H$14,H$13,0)))) | I3: =MAX(0,H3+H3*Setup!$C$7/1200-(IF(H3<=0,0,Setup!$D$7+IF($BL3=I$14,I$13,0)))) | J3: =MAX(0,I3+I3*Setup!$C$7/1200-(IF(I3<=0,0,Setup!$D$7+IF($BL3=J$14,J$13,0)))) | ... BJ3: =MAX(0,BI3+BI3*Setup!$C$7/1200-(IF(BI3<=0,0,Setup!$D$7+IF($BL3=BJ$14,BJ$13,0)))) | BL3: =IF(Setup!B7="",9999999,IF($BM$1="Snowball",Setup!B7,1-Setup!C7/100))+(ROW()-2)*0.00001
A4: =Setup!A8 | B4: =IF(Setup!B8="",0,Setup!B8) | C4: =MAX(0,B4+B4*Setup!$C$8/1200-(IF(B4<=0,0,Setup!$D$8+IF($BL4=C$14,C$13,0)))) | D4: =MAX(0,C4+C4*Setup!$C$8/1200-(IF(C4<=0,0,Setup!$D$8+IF($BL4=D$14,D$13,0)))) | E4: =MAX(0,D4+D4*Setup!$C$8/1200-(IF(D4<=0,0,Setup!$D$8+IF($BL4=E$14,E$13,0)))) | F4: =MAX(0,E4+E4*Setup!$C$8/1200-(IF(E4<=0,0,Setup!$D$8+IF($BL4=F$14,F$13,0)))) | G4: =MAX(0,F4+F4*Setup!$C$8/1200-(IF(F4<=0,0,Setup!$D$8+IF($BL4=G$14,G$13,0)))) | H4: =MAX(0,G4+G4*Setup!$C$8/1200-(IF(G4<=0,0,Setup!$D$8+IF($BL4=H$14,H$13,0)))) | I4: =MAX(0,H4+H4*Setup!$C$8/1200-(IF(H4<=0,0,Setup!$D$8+IF($BL4=I$14,I$13,0)))) | J4: =MAX(0,I4+I4*Setup!$C$8/1200-(IF(I4<=0,0,Setup!$D$8+IF($BL4=J$14,J$13,0)))) | ... BJ4: =MAX(0,BI4+BI4*Setup!$C$8/1200-(IF(BI4<=0,0,Setup!$D$8+IF($BL4=BJ$14,BJ$13,0)))) | BL4: =IF(Setup!B8="",9999999,IF($BM$1="Snowball",Setup!B8,1-Setup!C8/100))+(ROW()-2)*0.00001
A5: =Setup!A9 | B5: =IF(Setup!B9="",0,Setup!B9) | C5: =MAX(0,B5+B5*Setup!$C$9/1200-(IF(B5<=0,0,Setup!$D$9+IF($BL5=C$14,C$13,0)))) | D5: =MAX(0,C5+C5*Setup!$C$9/1200-(IF(C5<=0,0,Setup!$D$9+IF($BL5=D$14,D$13,0)))) | E5: =MAX(0,D5+D5*Setup!$C$9/1200-(IF(D5<=0,0,Setup!$D$9+IF($BL5=E$14,E$13,0)))) | F5: =MAX(0,E5+E5*Setup!$C$9/1200-(IF(E5<=0,0,Setup!$D$9+IF($BL5=F$14,F$13,0)))) | G5: =MAX(0,F5+F5*Setup!$C$9/1200-(IF(F5<=0,0,Setup!$D$9+IF($BL5=G$14,G$13,0)))) | H5: =MAX(0,G5+G5*Setup!$C$9/1200-(IF(G5<=0,0,Setup!$D$9+IF($BL5=H$14,H$13,0)))) | I5: =MAX(0,H5+H5*Setup!$C$9/1200-(IF(H5<=0,0,Setup!$D$9+IF($BL5=I$14,I$13,0)))) | J5: =MAX(0,I5+I5*Setup!$C$9/1200-(IF(I5<=0,0,Setup!$D$9+IF($BL5=J$14,J$13,0)))) | ... BJ5: =MAX(0,BI5+BI5*Setup!$C$9/1200-(IF(BI5<=0,0,Setup!$D$9+IF($BL5=BJ$14,BJ$13,0)))) | BL5: =IF(Setup!B9="",9999999,IF($BM$1="Snowball",Setup!B9,1-Setup!C9/100))+(ROW()-2)*0.00001
A6: =Setup!A10 | B6: =IF(Setup!B10="",0,Setup!B10) | C6: =MAX(0,B6+B6*Setup!$C$10/1200-(IF(B6<=0,0,Setup!$D$10+IF($BL6=C$14,C$13,0)))) | D6: =MAX(0,C6+C6*Setup!$C$10/1200-(IF(C6<=0,0,Setup!$D$10+IF($BL6=D$14,D$13,0)))) | E6: =MAX(0,D6+D6*Setup!$C$10/1200-(IF(D6<=0,0,Setup!$D$10+IF($BL6=E$14,E$13,0)))) | F6: =MAX(0,E6+E6*Setup!$C$10/1200-(IF(E6<=0,0,Setup!$D$10+IF($BL6=F$14,F$13,0)))) | G6: =MAX(0,F6+F6*Setup!$C$10/1200-(IF(F6<=0,0,Setup!$D$10+IF($BL6=G$14,G$13,0)))) | H6: =MAX(0,G6+G6*Setup!$C$10/1200-(IF(G6<=0,0,Setup!$D$10+IF($BL6=H$14,H$13,0)))) | I6: =MAX(0,H6+H6*Setup!$C$10/1200-(IF(H6<=0,0,Setup!$D$10+IF($BL6=I$14,I$13,0)))) | J6: =MAX(0,I6+I6*Setup!$C$10/1200-(IF(I6<=0,0,Setup!$D$10+IF($BL6=J$14,J$13,0)))) | ... BJ6: =MAX(0,BI6+BI6*Setup!$C$10/1200-(IF(BI6<=0,0,Setup!$D$10+IF($BL6=BJ$14,BJ$13,0)))) | BL6: =IF(Setup!B10="",9999999,IF($BM$1="Snowball",Setup!B10,1-Setup!C10/100))+(ROW()-2)*0.00001
A7: =Setup!A11 | B7: =IF(Setup!B11="",0,Setup!B11) | C7: =MAX(0,B7+B7*Setup!$C$11/1200-(IF(B7<=0,0,Setup!$D$11+IF($BL7=C$14,C$13,0)))) | D7: =MAX(0,C7+C7*Setup!$C$11/1200-(IF(C7<=0,0,Setup!$D$11+IF($BL7=D$14,D$13,0)))) | E7: =MAX(0,D7+D7*Setup!$C$11/1200-(IF(D7<=0,0,Setup!$D$11+IF($BL7=E$14,E$13,0)))) | F7: =MAX(0,E7+E7*Setup!$C$11/1200-(IF(E7<=0,0,Setup!$D$11+IF($BL7=F$14,F$13,0)))) | G7: =MAX(0,F7+F7*Setup!$C$11/1200-(IF(F7<=0,0,Setup!$D$11+IF($BL7=G$14,G$13,0)))) | H7: =MAX(0,G7+G7*Setup!$C$11/1200-(IF(G7<=0,0,Setup!$D$11+IF($BL7=H$14,H$13,0)))) | I7: =MAX(0,H7+H7*Setup!$C$11/1200-(IF(H7<=0,0,Setup!$D$11+IF($BL7=I$14,I$13,0)))) | J7: =MAX(0,I7+I7*Setup!$C$11/1200-(IF(I7<=0,0,Setup!$D$11+IF($BL7=J$14,J$13,0)))) | ... BJ7: =MAX(0,BI7+BI7*Setup!$C$11/1200-(IF(BI7<=0,0,Setup!$D$11+IF($BL7=BJ$14,BJ$13,0)))) | BL7: =IF(Setup!B11="",9999999,IF($BM$1="Snowball",Setup!B11,1-Setup!C11/100))+(ROW()-2)*0.00001
A8: =Setup!A12 | B8: =IF(Setup!B12="",0,Setup!B12) | C8: =MAX(0,B8+B8*Setup!$C$12/1200-(IF(B8<=0,0,Setup!$D$12+IF($BL8=C$14,C$13,0)))) | D8: =MAX(0,C8+C8*Setup!$C$12/1200-(IF(C8<=0,0,Setup!$D$12+IF($BL8=D$14,D$13,0)))) | E8: =MAX(0,D8+D8*Setup!$C$12/1200-(IF(D8<=0,0,Setup!$D$12+IF($BL8=E$14,E$13,0)))) | F8: =MAX(0,E8+E8*Setup!$C$12/1200-(IF(E8<=0,0,Setup!$D$12+IF($BL8=F$14,F$13,0)))) | G8: =MAX(0,F8+F8*Setup!$C$12/1200-(IF(F8<=0,0,Setup!$D$12+IF($BL8=G$14,G$13,0)))) | H8: =MAX(0,G8+G8*Setup!$C$12/1200-(IF(G8<=0,0,Setup!$D$12+IF($BL8=H$14,H$13,0)))) | I8: =MAX(0,H8+H8*Setup!$C$12/1200-(IF(H8<=0,0,Setup!$D$12+IF($BL8=I$14,I$13,0)))) | J8: =MAX(0,I8+I8*Setup!$C$12/1200-(IF(I8<=0,0,Setup!$D$12+IF($BL8=J$14,J$13,0)))) | ... BJ8: =MAX(0,BI8+BI8*Setup!$C$12/1200-(IF(BI8<=0,0,Setup!$D$12+IF($BL8=BJ$14,BJ$13,0)))) | BL8: =IF(Setup!B12="",9999999,IF($BM$1="Snowball",Setup!B12,1-Setup!C12/100))+(ROW()-2)*0.00001
A9: =Setup!A13 | B9: =IF(Setup!B13="",0,Setup!B13) | C9: =MAX(0,B9+B9*Setup!$C$13/1200-(IF(B9<=0,0,Setup!$D$13+IF($BL9=C$14,C$13,0)))) | D9: =MAX(0,C9+C9*Setup!$C$13/1200-(IF(C9<=0,0,Setup!$D$13+IF($BL9=D$14,D$13,0)))) | E9: =MAX(0,D9+D9*Setup!$C$13/1200-(IF(D9<=0,0,Setup!$D$13+IF($BL9=E$14,E$13,0)))) | F9: =MAX(0,E9+E9*Setup!$C$13/1200-(IF(E9<=0,0,Setup!$D$13+IF($BL9=F$14,F$13,0)))) | G9: =MAX(0,F9+F9*Setup!$C$13/1200-(IF(F9<=0,0,Setup!$D$13+IF($BL9=G$14,G$13,0)))) | H9: =MAX(0,G9+G9*Setup!$C$13/1200-(IF(G9<=0,0,Setup!$D$13+IF($BL9=H$14,H$13,0)))) | I9: =MAX(0,H9+H9*Setup!$C$13/1200-(IF(H9<=0,0,Setup!$D$13+IF($BL9=I$14,I$13,0)))) | J9: =MAX(0,I9+I9*Setup!$C$13/1200-(IF(I9<=0,0,Setup!$D$13+IF($BL9=J$14,J$13,0)))) | ... BJ9: =MAX(0,BI9+BI9*Setup!$C$13/1200-(IF(BI9<=0,0,Setup!$D$13+IF($BL9=BJ$14,BJ$13,0)))) | BL9: =IF(Setup!B13="",9999999,IF($BM$1="Snowball",Setup!B13,1-Setup!C13/100))+(ROW()-2)*0.00001
A10: =Setup!A14 | B10: =IF(Setup!B14="",0,Setup!B14) | C10: =MAX(0,B10+B10*Setup!$C$14/1200-(IF(B10<=0,0,Setup!$D$14+IF($BL10=C$14,C$13,0)))) | D10: =MAX(0,C10+C10*Setup!$C$14/1200-(IF(C10<=0,0,Setup!$D$14+IF($BL10=D$14,D$13,0)))) | E10: =MAX(0,D10+D10*Setup!$C$14/1200-(IF(D10<=0,0,Setup!$D$14+IF($BL10=E$14,E$13,0)))) | F10: =MAX(0,E10+E10*Setup!$C$14/1200-(IF(E10<=0,0,Setup!$D$14+IF($BL10=F$14,F$13,0)))) | G10: =MAX(0,F10+F10*Setup!$C$14/1200-(IF(F10<=0,0,Setup!$D$14+IF($BL10=G$14,G$13,0)))) | H10: =MAX(0,G10+G10*Setup!$C$14/1200-(IF(G10<=0,0,Setup!$D$14+IF($BL10=H$14,H$13,0)))) | I10: =MAX(0,H10+H10*Setup!$C$14/1200-(IF(H10<=0,0,Setup!$D$14+IF($BL10=I$14,I$13,0)))) | J10: =MAX(0,I10+I10*Setup!$C$14/1200-(IF(I10<=0,0,Setup!$D$14+IF($BL10=J$14,J$13,0)))) | ... BJ10: =MAX(0,BI10+BI10*Setup!$C$14/1200-(IF(BI10<=0,0,Setup!$D$14+IF($BL10=BJ$14,BJ$13,0)))) | BL10: =IF(Setup!B14="",9999999,IF($BM$1="Snowball",Setup!B14,1-Setup!C14/100))+(ROW()-2)*0.00001
A11: =Setup!A15 | B11: =IF(Setup!B15="",0,Setup!B15) | C11: =MAX(0,B11+B11*Setup!$C$15/1200-(IF(B11<=0,0,Setup!$D$15+IF($BL11=C$14,C$13,0)))) | D11: =MAX(0,C11+C11*Setup!$C$15/1200-(IF(C11<=0,0,Setup!$D$15+IF($BL11=D$14,D$13,0)))) | E11: =MAX(0,D11+D11*Setup!$C$15/1200-(IF(D11<=0,0,Setup!$D$15+IF($BL11=E$14,E$13,0)))) | F11: =MAX(0,E11+E11*Setup!$C$15/1200-(IF(E11<=0,0,Setup!$D$15+IF($BL11=F$14,F$13,0)))) | G11: =MAX(0,F11+F11*Setup!$C$15/1200-(IF(F11<=0,0,Setup!$D$15+IF($BL11=G$14,G$13,0)))) | H11: =MAX(0,G11+G11*Setup!$C$15/1200-(IF(G11<=0,0,Setup!$D$15+IF($BL11=H$14,H$13,0)))) | I11: =MAX(0,H11+H11*Setup!$C$15/1200-(IF(H11<=0,0,Setup!$D$15+IF($BL11=I$14,I$13,0)))) | J11: =MAX(0,I11+I11*Setup!$C$15/1200-(IF(I11<=0,0,Setup!$D$15+IF($BL11=J$14,J$13,0)))) | ... BJ11: =MAX(0,BI11+BI11*Setup!$C$15/1200-(IF(BI11<=0,0,Setup!$D$15+IF($BL11=BJ$14,BJ$13,0)))) | BL11: =IF(Setup!B15="",9999999,IF($BM$1="Snowball",Setup!B15,1-Setup!C15/100))+(ROW()-2)*0.00001
A12: =Setup!A16 | B12: =IF(Setup!B16="",0,Setup!B16) | C12: =MAX(0,B12+B12*Setup!$C$16/1200-(IF(B12<=0,0,Setup!$D$16+IF($BL12=C$14,C$13,0)))) | D12: =MAX(0,C12+C12*Setup!$C$16/1200-(IF(C12<=0,0,Setup!$D$16+IF($BL12=D$14,D$13,0)))) | E12: =MAX(0,D12+D12*Setup!$C$16/1200-(IF(D12<=0,0,Setup!$D$16+IF($BL12=E$14,E$13,0)))) | F12: =MAX(0,E12+E12*Setup!$C$16/1200-(IF(E12<=0,0,Setup!$D$16+IF($BL12=F$14,F$13,0)))) | G12: =MAX(0,F12+F12*Setup!$C$16/1200-(IF(F12<=0,0,Setup!$D$16+IF($BL12=G$14,G$13,0)))) | H12: =MAX(0,G12+G12*Setup!$C$16/1200-(IF(G12<=0,0,Setup!$D$16+IF($BL12=H$14,H$13,0)))) | I12: =MAX(0,H12+H12*Setup!$C$16/1200-(IF(H12<=0,0,Setup!$D$16+IF($BL12=I$14,I$13,0)))) | J12: =MAX(0,I12+I12*Setup!$C$16/1200-(IF(I12<=0,0,Setup!$D$16+IF($BL12=J$14,J$13,0)))) | ... BJ12: =MAX(0,BI12+BI12*Setup!$C$16/1200-(IF(BI12<=0,0,Setup!$D$16+IF($BL12=BJ$14,BJ$13,0)))) | BL12: =IF(Setup!B16="",9999999,IF($BM$1="Snowball",Setup!B16,1-Setup!C16/100))+(ROW()-2)*0.00001
A13: pool | C13: =Setup!$I$4+SUMIFS(Setup!$D$7:$D$16,Compare!$B$3:$B$12,"=0") | D13: =Setup!$I$4+SUMIFS(Setup!$D$7:$D$16,Compare!$C$3:$C$12,"=0") | E13: =Setup!$I$4+SUMIFS(Setup!$D$7:$D$16,Compare!$D$3:$D$12,"=0") | F13: =Setup!$I$4+SUMIFS(Setup!$D$7:$D$16,Compare!$E$3:$E$12,"=0") | G13: =Setup!$I$4+SUMIFS(Setup!$D$7:$D$16,Compare!$F$3:$F$12,"=0") | H13: =Setup!$I$4+SUMIFS(Setup!$D$7:$D$16,Compare!$G$3:$G$12,"=0") | I13: =Setup!$I$4+SUMIFS(Setup!$D$7:$D$16,Compare!$H$3:$H$12,"=0") | J13: =Setup!$I$4+SUMIFS(Setup!$D$7:$D$16,Compare!$I$3:$I$12,"=0") | K13: =Setup!$I$4+SUMIFS(Setup!$D$7:$D$16,Compare!$J$3:$J$12,"=0") | L13: =Setup!$I$4+SUMIFS(Setup!$D$7:$D$16,Compare!$K$3:$K$12,"=0") | M13: =Setup!$I$4+SUMIFS(Setup!$D$7:$D$16,Compare!$L$3:$L$12,"=0") | N13: =Setup!$I$4+SUMIFS(Setup!$D$7:$D$16,Compare!$M$3:$M$12,"=0") | O13: =Setup!$I$4+SUMIFS(Setup!$D$7:$D$16,Compare!$N$3:$N$12,"=0") | P13: =Setup!$I$4+SUMIFS(Setup!$D$7:$D$16,Compare!$O$3:$O$12,"=0") | Q13: =Setup!$I$4+SUMIFS(Setup!$D$7:$D$16,Compare!$P$3:$P$12,"=0") | R13: =Setup!$I$4+SUMIFS(Setup!$D$7:$D$16,Compare!$Q$3:$Q$12,"=0") | S13: =Setup!$I$4+SUMIFS(Setup!$D$7:$D$16,Compare!$R$3:$R$12,"=0") | T13: =Setup!$I$4+SUMIFS(Setup!$D$7:$D$16,Compare!$S$3:$S$12,"=0") | U13: =Setup!$I$4+SUMIFS(Setup!$D$7:$D$16,Compare!$T$3:$T$12,"=0") | V13: =Setup!$I$4+SUMIFS(Setup!$D$7:$D$16,Compare!$U$3:$U$12,"=0") | W13: =Setup!$I$4+SUMIFS(Setup!$D$7:$D$16,Compare!$V$3:$V$12,"=0") | X13: =Setup!$I$4+SUMIFS(Setup!$D$7:$D$16,Compare!$W$3:$W$12,"=0") | Y13: =Setup!$I$4+SUMIFS(Setup!$D$7:$D$16,Compare!$X$3:$X$12,"=0") | Z13: =Setup!$I$4+SUMIFS(Setup!$D$7:$D$16,Compare!$Y$3:$Y$12,"=0") | AA13: =Setup!$I$4+SUMIFS(Setup!$D$7:$D$16,Compare!$Z$3:$Z$12,"=0") | AB13: =Setup!$I$4+SUMIFS(Setup!$D$7:$D$16,Compare!$AA$3:$AA$12,"=0") | AC13: =Setup!$I$4+SUMIFS(Setup!$D$7:$D$16,Compare!$AB$3:$AB$12,"=0") | AD13: =Setup!$I$4+SUMIFS(Setup!$D$7:$D$16,Compare!$AC$3:$AC$12,"=0") | AE13: =Setup!$I$4+SUMIFS(Setup!$D$7:$D$16,Compare!$AD$3:$AD$12,"=0") | AF13: =Setup!$I$4+SUMIFS(Setup!$D$7:$D$16,Compare!$AE$3:$AE$12,"=0") | AG13: =Setup!$I$4+SUMIFS(Setup!$D$7:$D$16,Compare!$AF$3:$AF$12,"=0") | AH13: =Setup!$I$4+SUMIFS(Setup!$D$7:$D$16,Compare!$AG$3:$AG$12,"=0") | AI13: =Setup!$I$4+SUMIFS(Setup!$D$7:$D$16,Compare!$AH$3:$AH$12,"=0") | AJ13: =Setup!$I$4+SUMIFS(Setup!$D$7:$D$16,Compare!$AI$3:$AI$12,"=0") | AK13: =Setup!$I$4+SUMIFS(Setup!$D$7:$D$16,Compare!$AJ$3:$AJ$12,"=0") | AL13: =Setup!$I$4+SUMIFS(Setup!$D$7:$D$16,Compare!$AK$3:$AK$12,"=0") | AM13: =Setup!$I$4+SUMIFS(Setup!$D$7:$D$16,Compare!$AL$3:$AL$12,"=0") | AN13: =Setup!$I$4+SUMIFS(Setup!$D$7:$D$16,Compare!$AM$3:$AM$12,"=0") | AO13: =Setup!$I$4+SUMIFS(Setup!$D$7:$D$16,Compare!$AN$3:$AN$12,"=0") | AP13: =Setup!$I$4+SUMIFS(Setup!$D$7:$D$16,Compare!$AO$3:$AO$12,"=0") | AQ13: =Setup!$I$4+SUMIFS(Setup!$D$7:$D$16,Compare!$AP$3:$AP$12,"=0") | AR13: =Setup!$I$4+SUMIFS(Setup!$D$7:$D$16,Compare!$AQ$3:$AQ$12,"=0") | AS13: =Setup!$I$4+SUMIFS(Setup!$D$7:$D$16,Compare!$AR$3:$AR$12,"=0") | AT13: =Setup!$I$4+SUMIFS(Setup!$D$7:$D$16,Compare!$AS$3:$AS$12,"=0") | AU13: =Setup!$I$4+SUMIFS(Setup!$D$7:$D$16,Compare!$AT$3:$AT$12,"=0") | AV13: =Setup!$I$4+SUMIFS(Setup!$D$7:$D$16,Compare!$AU$3:$AU$12,"=0") | AW13: =Setup!$I$4+SUMIFS(Setup!$D$7:$D$16,Compare!$AV$3:$AV$12,"=0") | AX13: =Setup!$I$4+SUMIFS(Setup!$D$7:$D$16,Compare!$AW$3:$AW$12,"=0") | AY13: =Setup!$I$4+SUMIFS(Setup!$D$7:$D$16,Compare!$AX$3:$AX$12,"=0") | AZ13: =Setup!$I$4+SUMIFS(Setup!$D$7:$D$16,Compare!$AY$3:$AY$12,"=0") | BA13: =Setup!$I$4+SUMIFS(Setup!$D$7:$D$16,Compare!$AZ$3:$AZ$12,"=0") | BB13: =Setup!$I$4+SUMIFS(Setup!$D$7:$D$16,Compare!$BA$3:$BA$12,"=0") | BC13: =Setup!$I$4+SUMIFS(Setup!$D$7:$D$16,Compare!$BB$3:$BB$12,"=0") | BD13: =Setup!$I$4+SUMIFS(Setup!$D$7:$D$16,Compare!$BC$3:$BC$12,"=0") | BE13: =Setup!$I$4+SUMIFS(Setup!$D$7:$D$16,Compare!$BD$3:$BD$12,"=0") | BF13: =Setup!$I$4+SUMIFS(Setup!$D$7:$D$16,Compare!$BE$3:$BE$12,"=0") | BG13: =Setup!$I$4+SUMIFS(Setup!$D$7:$D$16,Compare!$BF$3:$BF$12,"=0") | BH13: =Setup!$I$4+SUMIFS(Setup!$D$7:$D$16,Compare!$BG$3:$BG$12,"=0") | BI13: =Setup!$I$4+SUMIFS(Setup!$D$7:$D$16,Compare!$BH$3:$BH$12,"=0") | BJ13: =Setup!$I$4+SUMIFS(Setup!$D$7:$D$16,Compare!$BI$3:$BI$12,"=0")
A14: priority score | C14: =_xlfn.MINIFS($BL$3:$BL$12,Compare!$B$3:$B$12,">0") | D14: =_xlfn.MINIFS($BL$3:$BL$12,Compare!$C$3:$C$12,">0") | E14: =_xlfn.MINIFS($BL$3:$BL$12,Compare!$D$3:$D$12,">0") | F14: =_xlfn.MINIFS($BL$3:$BL$12,Compare!$E$3:$E$12,">0") | G14: =_xlfn.MINIFS($BL$3:$BL$12,Compare!$F$3:$F$12,">0") | H14: =_xlfn.MINIFS($BL$3:$BL$12,Compare!$G$3:$G$12,">0") | I14: =_xlfn.MINIFS($BL$3:$BL$12,Compare!$H$3:$H$12,">0") | J14: =_xlfn.MINIFS($BL$3:$BL$12,Compare!$I$3:$I$12,">0") | K14: =_xlfn.MINIFS($BL$3:$BL$12,Compare!$J$3:$J$12,">0") | L14: =_xlfn.MINIFS($BL$3:$BL$12,Compare!$K$3:$K$12,">0") | M14: =_xlfn.MINIFS($BL$3:$BL$12,Compare!$L$3:$L$12,">0") | N14: =_xlfn.MINIFS($BL$3:$BL$12,Compare!$M$3:$M$12,">0") | O14: =_xlfn.MINIFS($BL$3:$BL$12,Compare!$N$3:$N$12,">0") | P14: =_xlfn.MINIFS($BL$3:$BL$12,Compare!$O$3:$O$12,">0") | Q14: =_xlfn.MINIFS($BL$3:$BL$12,Compare!$P$3:$P$12,">0") | R14: =_xlfn.MINIFS($BL$3:$BL$12,Compare!$Q$3:$Q$12,">0") | S14: =_xlfn.MINIFS($BL$3:$BL$12,Compare!$R$3:$R$12,">0") | T14: =_xlfn.MINIFS($BL$3:$BL$12,Compare!$S$3:$S$12,">0") | U14: =_xlfn.MINIFS($BL$3:$BL$12,Compare!$T$3:$T$12,">0") | V14: =_xlfn.MINIFS($BL$3:$BL$12,Compare!$U$3:$U$12,">0") | W14: =_xlfn.MINIFS($BL$3:$BL$12,Compare!$V$3:$V$12,">0") | X14: =_xlfn.MINIFS($BL$3:$BL$12,Compare!$W$3:$W$12,">0") | Y14: =_xlfn.MINIFS($BL$3:$BL$12,Compare!$X$3:$X$12,">0") | Z14: =_xlfn.MINIFS($BL$3:$BL$12,Compare!$Y$3:$Y$12,">0") | AA14: =_xlfn.MINIFS($BL$3:$BL$12,Compare!$Z$3:$Z$12,">0") | AB14: =_xlfn.MINIFS($BL$3:$BL$12,Compare!$AA$3:$AA$12,">0") | AC14: =_xlfn.MINIFS($BL$3:$BL$12,Compare!$AB$3:$AB$12,">0") | AD14: =_xlfn.MINIFS($BL$3:$BL$12,Compare!$AC$3:$AC$12,">0") | AE14: =_xlfn.MINIFS($BL$3:$BL$12,Compare!$AD$3:$AD$12,">0") | AF14: =_xlfn.MINIFS($BL$3:$BL$12,Compare!$AE$3:$AE$12,">0") | AG14: =_xlfn.MINIFS($BL$3:$BL$12,Compare!$AF$3:$AF$12,">0") | AH14: =_xlfn.MINIFS($BL$3:$BL$12,Compare!$AG$3:$AG$12,">0") | AI14: =_xlfn.MINIFS($BL$3:$BL$12,Compare!$AH$3:$AH$12,">0") | AJ14: =_xlfn.MINIFS($BL$3:$BL$12,Compare!$AI$3:$AI$12,">0") | AK14: =_xlfn.MINIFS($BL$3:$BL$12,Compare!$AJ$3:$AJ$12,">0") | AL14: =_xlfn.MINIFS($BL$3:$BL$12,Compare!$AK$3:$AK$12,">0") | AM14: =_xlfn.MINIFS($BL$3:$BL$12,Compare!$AL$3:$AL$12,">0") | AN14: =_xlfn.MINIFS($BL$3:$BL$12,Compare!$AM$3:$AM$12,">0") | AO14: =_xlfn.MINIFS($BL$3:$BL$12,Compare!$AN$3:$AN$12,">0") | AP14: =_xlfn.MINIFS($BL$3:$BL$12,Compare!$AO$3:$AO$12,">0") | AQ14: =_xlfn.MINIFS($BL$3:$BL$12,Compare!$AP$3:$AP$12,">0") | AR14: =_xlfn.MINIFS($BL$3:$BL$12,Compare!$AQ$3:$AQ$12,">0") | AS14: =_xlfn.MINIFS($BL$3:$BL$12,Compare!$AR$3:$AR$12,">0") | AT14: =_xlfn.MINIFS($BL$3:$BL$12,Compare!$AS$3:$AS$12,">0") | AU14: =_xlfn.MINIFS($BL$3:$BL$12,Compare!$AT$3:$AT$12,">0") | AV14: =_xlfn.MINIFS($BL$3:$BL$12,Compare!$AU$3:$AU$12,">0") | AW14: =_xlfn.MINIFS($BL$3:$BL$12,Compare!$AV$3:$AV$12,">0") | AX14: =_xlfn.MINIFS($BL$3:$BL$12,Compare!$AW$3:$AW$12,">0") | AY14: =_xlfn.MINIFS($BL$3:$BL$12,Compare!$AX$3:$AX$12,">0") | AZ14: =_xlfn.MINIFS($BL$3:$BL$12,Compare!$AY$3:$AY$12,">0") | BA14: =_xlfn.MINIFS($BL$3:$BL$12,Compare!$AZ$3:$AZ$12,">0") | BB14: =_xlfn.MINIFS($BL$3:$BL$12,Compare!$BA$3:$BA$12,">0") | BC14: =_xlfn.MINIFS($BL$3:$BL$12,Compare!$BB$3:$BB$12,">0") | BD14: =_xlfn.MINIFS($BL$3:$BL$12,Compare!$BC$3:$BC$12,">0") | BE14: =_xlfn.MINIFS($BL$3:$BL$12,Compare!$BD$3:$BD$12,">0") | BF14: =_xlfn.MINIFS($BL$3:$BL$12,Compare!$BE$3:$BE$12,">0") | BG14: =_xlfn.MINIFS($BL$3:$BL$12,Compare!$BF$3:$BF$12,">0") | BH14: =_xlfn.MINIFS($BL$3:$BL$12,Compare!$BG$3:$BG$12,">0") | BI14: =_xlfn.MINIFS($BL$3:$BL$12,Compare!$BH$3:$BH$12,">0") | BJ14: =_xlfn.MINIFS($BL$3:$BL$12,Compare!$BI$3:$BI$12,">0")
A15: total balance | B15: =SUM(B3:B12) | C15: =SUM(C3:C12) | D15: =SUM(D3:D12) | E15: =SUM(E3:E12) | F15: =SUM(F3:F12) | G15: =SUM(G3:G12) | H15: =SUM(H3:H12) | I15: =SUM(I3:I12) | ... BJ15: =SUM(BJ3:BJ12)
A16: interest | C16: =SUMPRODUCT(Compare!$B$3:$B$12,Setup!$C$7:$C$16)/1200 | D16: =SUMPRODUCT(Compare!$C$3:$C$12,Setup!$C$7:$C$16)/1200 | E16: =SUMPRODUCT(Compare!$D$3:$D$12,Setup!$C$7:$C$16)/1200 | F16: =SUMPRODUCT(Compare!$E$3:$E$12,Setup!$C$7:$C$16)/1200 | G16: =SUMPRODUCT(Compare!$F$3:$F$12,Setup!$C$7:$C$16)/1200 | H16: =SUMPRODUCT(Compare!$G$3:$G$12,Setup!$C$7:$C$16)/1200 | I16: =SUMPRODUCT(Compare!$H$3:$H$12,Setup!$C$7:$C$16)/1200 | J16: =SUMPRODUCT(Compare!$I$3:$I$12,Setup!$C$7:$C$16)/1200 | K16: =SUMPRODUCT(Compare!$J$3:$J$12,Setup!$C$7:$C$16)/1200 | L16: =SUMPRODUCT(Compare!$K$3:$K$12,Setup!$C$7:$C$16)/1200 | M16: =SUMPRODUCT(Compare!$L$3:$L$12,Setup!$C$7:$C$16)/1200 | N16: =SUMPRODUCT(Compare!$M$3:$M$12,Setup!$C$7:$C$16)/1200 | O16: =SUMPRODUCT(Compare!$N$3:$N$12,Setup!$C$7:$C$16)/1200 | P16: =SUMPRODUCT(Compare!$O$3:$O$12,Setup!$C$7:$C$16)/1200 | Q16: =SUMPRODUCT(Compare!$P$3:$P$12,Setup!$C$7:$C$16)/1200 | R16: =SUMPRODUCT(Compare!$Q$3:$Q$12,Setup!$C$7:$C$16)/1200 | S16: =SUMPRODUCT(Compare!$R$3:$R$12,Setup!$C$7:$C$16)/1200 | T16: =SUMPRODUCT(Compare!$S$3:$S$12,Setup!$C$7:$C$16)/1200 | U16: =SUMPRODUCT(Compare!$T$3:$T$12,Setup!$C$7:$C$16)/1200 | V16: =SUMPRODUCT(Compare!$U$3:$U$12,Setup!$C$7:$C$16)/1200 | W16: =SUMPRODUCT(Compare!$V$3:$V$12,Setup!$C$7:$C$16)/1200 | X16: =SUMPRODUCT(Compare!$W$3:$W$12,Setup!$C$7:$C$16)/1200 | Y16: =SUMPRODUCT(Compare!$X$3:$X$12,Setup!$C$7:$C$16)/1200 | Z16: =SUMPRODUCT(Compare!$Y$3:$Y$12,Setup!$C$7:$C$16)/1200 | AA16: =SUMPRODUCT(Compare!$Z$3:$Z$12,Setup!$C$7:$C$16)/1200 | AB16: =SUMPRODUCT(Compare!$AA$3:$AA$12,Setup!$C$7:$C$16)/1200 | AC16: =SUMPRODUCT(Compare!$AB$3:$AB$12,Setup!$C$7:$C$16)/1200 | AD16: =SUMPRODUCT(Compare!$AC$3:$AC$12,Setup!$C$7:$C$16)/1200 | AE16: =SUMPRODUCT(Compare!$AD$3:$AD$12,Setup!$C$7:$C$16)/1200 | AF16: =SUMPRODUCT(Compare!$AE$3:$AE$12,Setup!$C$7:$C$16)/1200 | AG16: =SUMPRODUCT(Compare!$AF$3:$AF$12,Setup!$C$7:$C$16)/1200 | AH16: =SUMPRODUCT(Compare!$AG$3:$AG$12,Setup!$C$7:$C$16)/1200 | AI16: =SUMPRODUCT(Compare!$AH$3:$AH$12,Setup!$C$7:$C$16)/1200 | AJ16: =SUMPRODUCT(Compare!$AI$3:$AI$12,Setup!$C$7:$C$16)/1200 | AK16: =SUMPRODUCT(Compare!$AJ$3:$AJ$12,Setup!$C$7:$C$16)/1200 | AL16: =SUMPRODUCT(Compare!$AK$3:$AK$12,Setup!$C$7:$C$16)/1200 | AM16: =SUMPRODUCT(Compare!$AL$3:$AL$12,Setup!$C$7:$C$16)/1200 | AN16: =SUMPRODUCT(Compare!$AM$3:$AM$12,Setup!$C$7:$C$16)/1200 | AO16: =SUMPRODUCT(Compare!$AN$3:$AN$12,Setup!$C$7:$C$16)/1200 | AP16: =SUMPRODUCT(Compare!$AO$3:$AO$12,Setup!$C$7:$C$16)/1200 | AQ16: =SUMPRODUCT(Compare!$AP$3:$AP$12,Setup!$C$7:$C$16)/1200 | AR16: =SUMPRODUCT(Compare!$AQ$3:$AQ$12,Setup!$C$7:$C$16)/1200 | AS16: =SUMPRODUCT(Compare!$AR$3:$AR$12,Setup!$C$7:$C$16)/1200 | AT16: =SUMPRODUCT(Compare!$AS$3:$AS$12,Setup!$C$7:$C$16)/1200 | AU16: =SUMPRODUCT(Compare!$AT$3:$AT$12,Setup!$C$7:$C$16)/1200 | AV16: =SUMPRODUCT(Compare!$AU$3:$AU$12,Setup!$C$7:$C$16)/1200 | AW16: =SUMPRODUCT(Compare!$AV$3:$AV$12,Setup!$C$7:$C$16)/1200 | AX16: =SUMPRODUCT(Compare!$AW$3:$AW$12,Setup!$C$7:$C$16)/1200 | AY16: =SUMPRODUCT(Compare!$AX$3:$AX$12,Setup!$C$7:$C$16)/1200 | AZ16: =SUMPRODUCT(Compare!$AY$3:$AY$12,Setup!$C$7:$C$16)/1200 | BA16: =SUMPRODUCT(Compare!$AZ$3:$AZ$12,Setup!$C$7:$C$16)/1200 | BB16: =SUMPRODUCT(Compare!$BA$3:$BA$12,Setup!$C$7:$C$16)/1200 | BC16: =SUMPRODUCT(Compare!$BB$3:$BB$12,Setup!$C$7:$C$16)/1200 | BD16: =SUMPRODUCT(Compare!$BC$3:$BC$12,Setup!$C$7:$C$16)/1200 | BE16: =SUMPRODUCT(Compare!$BD$3:$BD$12,Setup!$C$7:$C$16)/1200 | BF16: =SUMPRODUCT(Compare!$BE$3:$BE$12,Setup!$C$7:$C$16)/1200 | BG16: =SUMPRODUCT(Compare!$BF$3:$BF$12,Setup!$C$7:$C$16)/1200 | BH16: =SUMPRODUCT(Compare!$BG$3:$BG$12,Setup!$C$7:$C$16)/1200 | BI16: =SUMPRODUCT(Compare!$BH$3:$BH$12,Setup!$C$7:$C$16)/1200 | BJ16: =SUMPRODUCT(Compare!$BI$3:$BI$12,Setup!$C$7:$C$16)/1200
A18: =IFERROR(MATCH(0,Compare!$C$15:$BJ$15,0),0) | B18: months to debt-free (helper)
